Workbook

Sheet 00_Cover
C5: Nexus Technologies — Integrated Financial Model
B12: 3-Statement Model | Scenario Forecast | DCF Valuation
B14: Built from Project Atlas Gold Finance Warehouse
C17: © 2023 to 2026 Atlas Intelligence Platform
C18: Prepared by: Lewis Andrews
C19: Version: v0.1
C20: Currency: GBP
C21: Model period: Jan-2023 to Dec-2029

Sheet 01_Model_Map

Sheet 02_Control
A1: Nexus Technologies — Integrated Financial Model
A4: Control Panel
A5: ="Currency: "&B12&" | Units: "&B13&" | Version: "&B16 -> Currency: GBP | Units: £ actual | Version: v0.1
A7: Field | B7: Value
A8: Model Start Month | B8: 44927
A9: Actuals Through | B9: 46203 | L9: Scenario_List | M9: Units_List | N9: Reporting_Scope_List
A10: Forecast Start Month | B10: 46204 | L10: Base | M10: £ actual | N10: Company Total
A11: Forecast End Month | B11: 47453 | L11: Upside | M11: £000 | N11: Region Total
A12: Currency | B12: GBP | L12: Downside | M12: £m | N12: Business Unit Total
A13: Units | B13: £ actual
A14: Scenario | B14: Base
A15: Reporting Scope | B15: Company Total
A16: Model Version | B16: v0.1
A17: Last Updated | B17: =TODAY() -> 46204
A18: Unit Scale Factor | B18: {=_xlfn.SWITCH(B13,"£ actual",1,"£000",1000,"£m",1000000,1)} -> 1

Sheet 03_Raw_Exports
A1: Nexus Technologies — Raw Data Exports
A2: Source connection inventory (Power Query — Connection Only)
A3: Source Area | B3: File Name | C3: Query Name | D3: Load Type | E3: Status | F3: Notes
A4: Revenue | B4: mart_revenue_waterfall.csv | C4: src_revenue_waterfall | D4: Connection only | E4: Imported | F4: Recognition, billings, leakage
A5: O2C | B5: mart_o2c_customer_collections.csv | C5: src_o2c_customer_collections | D5: Connection only | E5: Imported | F5: Cash collected, AR exposure
A6: Deferred Revenue | B6: mart_deferred_revenue_control.csv | C6: src_deferred_revenue_control | D6: Connection only | E6: Imported | F6: Deferred revenue rollforward
A7: AP | B7: mart_ap_working_capital_control.csv | C7: src_ap_working_capital_control | D7: Connection only | E7: Imported | F7: Supplier spend, payments, AP
A8: Workforce | B8: mart_workforce_cost_control.csv | C8: src_workforce_cost_control | D8: Connection only | E8: Imported | F8: Payroll, FTE, hiring pressure
A9: SaaS ARR | B9: mart_saas_arr_movement.csv | C9: src_saas_arr_movement | D9: Connection only | E9: Imported | F9: ARR bridge
A10: SaaS Retention | B10: mart_saas_retention.csv | C10: src_saas_retention | D10: Connection only | E10: Imported | F10: GRR, NRR, churn

Sheet 04_Model_Feed_Final
A1: reporting_month_date | B1: billings_gbp | C1: recognised_revenue_actual_gbp | D1: recognised_revenue_total_gbp | E1: cash_collected_gbp | F1: net_unallocated_invoice_exposure_gbp | G1: open_ar_exposure_gbp | H1: revenue_vs_o2c_billings_variance_gbp | I1: revenue_vs_o2c_billings_status | J1: opening_deferred_revenue_gbp | K1: new_billings_deferred_revenue_gbp | L1: recognised_revenue_release_gbp | M1: closing_deferred_revenue_gbp | N1: deferred_revenue_model_variance_gbp | O1: deferred_revenue_model_status | P1: ap_invoice_spend_gbp | Q1: supplier_cash_paid_gbp | R1: open_ap_liability_gbp | S1: overdue_ap_liability_gbp | T1: dpo_proxy_days | U1: ap_control_status | V1: payroll_cost_gbp | W1: base_salary_cost_gbp | X1: employer_tax_cost_gbp | Y1: benefits_cost_gbp | Z1: bonus_accrual_cost_gbp | AA1: active_headcount_count | AB1: active_fte_count | AC1: model_payroll_cost_per_active_fte_gbp | AD1: workforce_control_status | AE1: beginning_arr_gbp | AF1: new_business_arr_gbp | AG1: expansion_arr_gbp | AH1: contraction_arr_gbp | AI1: churn_arr_gbp | AJ1: net_arr_delta_gbp | AK1: arr_monthly_run_rate_source_gbp | AL1: headline_arr_gbp | AM1: saas_arr_control_status | AN1: beginning_active_customer_count | AO1: ending_active_customer_count | AP1: churned_customer_count | AQ1: new_customer_count | AR1: gross_revenue_retention_rate | AS1: net_revenue_retention_rate | AT1: logo_churn_rate | AU1: new_customer_rate | AV1: saas_retention_control_status | AW1: actual_operating_expense_gbp | AX1: actual_operating_profit_gbp | AY1: actual_operating_margin | AZ1: revenue_per_active_fte_gbp | BA1: arr_net_movement_pct | BB1: period_type | BC1: arr_monthly_run_rate_from_active_gbp | BD1: arr_monthly_run_rate_variance_gbp | BE1: arr_bridge_calc_active_arr_gbp | BF1: arr_bridge_variance_gbp | BG1: arr_bridge_status | BH1: arr_monthly_run_rate_status
A2: 44927 | B2: 4257902.4 | C2: 1466626.4 | D2: 1466626.4 | E2: 3771182.3 | F2: 1066716.2 | G2: 1073080.8 | H2: -579996.06 | I2: Definition Difference | J2: -2902.5 | K2: 4257902.4 | L2: 1466626.4 | M2: 2788373.4 | N2: 0 | O2: OK | P2: 291150.19 | Q2: 2972.29 | R2: 0 | S2: 0 | T2: 0 | U2: OK | V2: 4641129.1 | W2: 3456488.9 | X2: 429099.94 | Y2: 343681.92 | Z2: 411858.31 | AA2: 452 | AB2: 452 | AC2: 10267.985 | AD2: Control Exception | AE2: 43815823 | AF2: 1121206 | AG2: 31446.48 | AH2: 7035 | AI2: 19440 | AJ2: 1126278.6 | AK2: 3744791.8 | AL2: 44911762 | AM2: Control Exception | AN2: 2273 | AO2: 2322 | AP2: 1 | AQ2: 55 | AR2: 0.99952588 | AS2: 1.0001135 | AT2: 0.00043994721 | AU2: 0.024197096 | AV2: Control Exception | AW2: 4932279.3 | AX2: -3465652.9 | AY2: -2.36301 | AZ2: 3244.7487 | BA2: 0.025704838 | BB2: Actual | BC2: 3742646.8 | BD2: 2145 | BE2: 44942102 | BF2: -30340 | BG2: Source Definition Difference | BH2: Rounding / Definition Difference
A3: 44958 | B3: 3516657.3 | C3: 1641714.9 | D3: 1641714.9 | E3: 3312454.7 | F3: 565960.16 | G3: 584121.35 | H3: -361757.55 | I3: Minor Variance | J3: 2788373.4 | K3: 3516657.3 | L3: 1641714.9 | M3: 4663315.8 | N3: 0 | O3: OK | P3: 658218.22 | Q3: 144978.52 | R3: 0 | S3: 0 | T3: 0 | U3: OK | V3: 4731102.6 | W3: 3523093.3 | X3: 436666.36 | Y3: 350456.63 | Z3: 420886.39 | AA3: 461 | AB3: 461 | AC3: 10262.696 | AD3: Control Exception | AE3: 44942102 | AF3: 1009401 | AG3: 34172.8 | AH3: 10911 | AI3: 28800 | AJ3: 1003863 | AK3: 3828430.4 | AL3: 45915625 | AM3: Control Exception | AN3: 2328 | AO3: 2377 | AP3: 2 | AQ3: 57 | AR3: 0.99924324 | AS3: 0.99987679 | AT3: 0.00085910653 | AU3: 0.024484536 | AV3: Control Exception | AW3: 5389320.9 | AX3: -3747605.9 | AY3: -2.2827385 | AZ3: 3561.2038 | BA3: 0.022336805 | BB3: Actual | BC3: 3826302.1 | BD3: 2128.3333 | BE3: 45945965 | BF3: -30340 | BG3: Source Definition Difference | BH3: Rounding / Definition Difference
A4: 44986 | B4: 3468525.1 | C4: 1917718.6 | D4: 1917718.6 | E4: 3172057.9 | F4: 730877.7 | G4: 740587.59 | H4: -434410.43 | I4: Definition Difference | J4: 4663315.8 | K4: 3468525.1 | L4: 1917718.6 | M4: 6214122.3 | N4: 0 | O4: OK | P4: 560331.15 | Q4: 806474.41 | R4: 0 | S4: 0 | T4: 0 | U4: OK | V4: 4807431.4 | W4: 3581160.7 | X4: 444946.58 | Y4: 355514.94 | Z4: 425809.18 | AA4: 476 | AB4: 476 | AC4: 10099.646 | AD4: Control Exception | AE4: 45945965 | AF4: 1217219 | AG4: 18291.36 | AH4: 0 | AI4: 24468 | AJ4: 1211241 | AK4: 3929333.8 | AL4: 47126866 | AM4: Control Exception | AN4: 2383 | AO4: 2436 | AP4: 2 | AQ4: 61 | AR4: 0.99959152 | AS4: 0.99986557 | AT4: 0.00083927822 | AU4: 0.025597986 | AV4: Control Exception | AW4: 5367762.6 | AX4: -3450043.9 | AY4: -1.7990355 | AZ4: 4028.8207 | BA4: 0.026362294 | BB4: Actual | BC4: 3927238.8 | BD4: 2095 | BE4: 47157206 | BF4: -30340 | BG4: Source Definition Difference | BH4: Rounding / Definition Difference
A5: 45017 | B5: 3871963.5 | C5: 2122884.7 | D5: 2122884.7 | E5: 3613516.5 | F5: 712640.92 | G5: 720385.8 | H5: -454194.01 | I5: Definition Difference | J5: 6214122.3 | K5: 3871963.5 | L5: 2122884.7 | M5: 7963201 | N5: 0 | O5: OK | P5: 755499.01 | Q5: 446431.7 | R5: 0 | S5: 0 | T5: 0 | U5: OK | V5: 4868707.2 | W5: 3627959.6 | X5: 450272.74 | Y5: 360066.75 | Z5: 430408.16 | AA5: 487 | AB5: 487 | AC5: 9997.3454 | AD5: Control Exception | AE5: 47157206 | AF5: 1002391 | AG5: 6058.32 | AH5: 15302 | AI5: 0 | AJ5: 993248.96 | AK5: 4012087.9 | AL5: 48120115 | AM5: Control Exception | AN5: 2442 | AO5: 2509 | AP5: 0 | AQ5: 73 | AR5: 0.9997964 | AS5: 0.999804 | AT5: 0 | AU5: 0.02989353 | AV5: Control Exception | AW5: 5624206.2 | AX5: -3501321.5 | AY5: -1.6493225 | AZ5: 4359.1062 | BA5: 0.021062507 | BB5: Actual | BC5: 4010009.6 | BD5: 2078.3333 | BE5: 48150455 | BF5: -30340 | BG5: Source Definition Difference | BH5: Rounding / Definition Difference
A6: 45047 | B6: 3491692.5 | C6: 2373771 | D6: 2373771 | E6: 3000694 | F6: 840106.9 | G6: 848665.75 | H6: -349108.41 | I6: Minor Variance | J6: 7963201 | K6: 3491692.5 | L6: 2373771 | M6: 9081122.6 | N6: 0 | O6: OK | P6: 519926.93 | Q6: 642419.77 | R6: 0 | S6: 0 | T6: 0 | U6: OK | V6: 4929130.6 | W6: 3672958.3 | X6: 456789.77 | Y6: 363721.88 | Z6: 435660.61 | AA6: 496 | AB6: 496 | AC6: 9937.7633 | AD6: Control Exception | AE6: 48150455 | AF6: 1529017 | AG6: 21306.72 | AH6: 0 | AI6: 6000 | AJ6: 1544522.9 | AK6: 4140773.1 | AL6: 49664638 | AM6: Control Exception | AN6: 2515 | AO6: 2590 | AP6: 1 | AQ6: 82 | AR6: 0.99999377 | AS6: 1.0003179 | AT6: 0.00039761431 | AU6: 0.032604374 | AV6: Control Exception | AW6: 5449057.5 | AX6: -3075286.5 | AY6: -1.2955279 | AZ6: 4785.8286 | BA6: 0.032077015 | BB6: Actual | BC6: 4138719.8 | BD6: 2053.3333 | BE6: 49694978 | BF6: -30340 | BG6: Source Definition Difference | BH6: Rounding / Definition Difference
A7: 45078 | B7: 4373359.3 | C7: 2624063.5 | D7: 2624063.5 | E7: 3983097.2 | F7: 903803.61 | G7: 917567.49 | H7: -513541.56 | I7: Definition Difference | J7: 9081122.6 | K7: 4373359.3 | L7: 2624063.5 | M7: 10830418 | N7: 0 | O7: OK | P7: 679161.62 | Q7: 500315.7 | R7: 0 | S7: 0 | T7: 0 | U7: OK | V7: 4974433.4 | W7: 3708519.4 | X7: 460709.5 | Y7: 367192.28 | Z7: 438012.17 | AA7: 505 | AB7: 505 | AC7: 9850.3631 | AD7: Control Exception | AE7: 49694978 | AF7: 1192700 | AG7: 60937.08 | AH7: 0 | AI7: 23868 | AJ7: 1230267.7 | AK7: 4243253.8 | AL7: 50894905 | AM7: Control Exception | AN7: 2596 | AO7: 2644 | AP7: 1 | AQ7: 55 | AR7: 0.99963441 | AS7: 1.0007459 | AT7: 0.00038520801 | AU7: 0.021186441 | AV7: Control Exception | AW7: 5653595 | AX7: -3029531.5 | AY7: -1.1545191 | AZ7: 5196.1654 | BA7: 0.024756379 | BB7: Actual | BC7: 4241242.1 | BD7: 2011.6667 | BE7: 50925245 | BF7: -30340 | BG7: Source Definition Difference | BH7: Rounding / Definition Difference
A8: 45108 | B8: 3788027.8 | C8: 2899362.8 | D8: 2899362.8 | E8: 3687227.4 | F8: 550712.28 | G8: 557672.58 | H8: -449911.95 | I8: Definition Difference | J8: 10830418 | K8: 3788027.8 | L8: 2899362.8 | M8: 11719083 | N8: 0 | O8: OK | P8: 588706.85 | Q8: 641704.78 | R8: 0 | S8: 0 | T8: 0 | U8: OK | V8: 5078537 | W8: 3782793.4 | X8: 472093.45 | Y8: 374057.7 | Z8: 449592.45 | AA8: 513 | AB8: 513 | AC8: 9899.6822 | AD8: Control Exception | AE8: 50925245 | AF8: 1062053 | AG8: 41914.44 | AH8: 0 | AI8: 0 | AJ8: 1111895.4 | AK8: 4335895 | AL8: 52006801 | AM8: Control Exception | AN8: 2650 | AO8: 2702 | AP8: 0 | AQ8: 57 | AR8: 1.0001119 | AS8: 1.0009787 | AT8: 0 | AU8: 0.021509434 | AV8: Control Exception | AW8: 5667243.8 | AX8: -2767881 | AY8: -0.95465151 | AZ8: 5651.7793 | BA8: 0.021833873 | BB8: Actual | BC8: 4333900.1 | BD8: 1995 | BE8: 52037141 | BF8: -30340 | BG8: Source Definition Difference | BH8: Rounding / Definition Difference
A9: 45139 | B9: 4187386.9 | C9: 3163202.6 | D9: 3163202.6 | E9: 4042353.8 | F9: 631174.55 | G9: 648072.02 | H9: -486141.47 | I9: Definition Difference | J9: 11719083 | K9: 4187386.9 | L9: 3163202.6 | M9: 12743268 | N9: 0 | O9: OK | P9: 863983.56 | Q9: 635031.87 | R9: 0 | S9: 0 | T9: 0 | U9: OK | V9: 5101870.2 | W9: 3800470.1 | X9: 473456.06 | Y9: 375661.95 | Z9: 452282.06 | AA9: 520 | AB9: 520 | AC9: 9811.2888 | AD9: Control Exception | AE9: 52037141 | AF9: 1428249 | AG9: 13973.16 | AH9: 10209 | AI9: 65430 | AJ9: 1366683.8 | AK9: 4449752 | AL9: 53373484 | AM9: Control Exception | AN9: 2708 | AO9: 2769 | AP9: 2 | AQ9: 69 | AR9: 0.998656 | AS9: 0.99881498 | AT9: 0.00073855244 | AU9: 0.025480059 | AV9: Control Exception | AW9: 5965853.7 | AX9: -2802651.1 | AY9: -0.88601695 | AZ9: 6083.0819 | BA9: 0.026263621 | BB9: Actual | BC9: 4447790.4 | BD9: 1961.6667 | BE9: 53403824 | BF9: -30340 | BG9: Source Definition Difference | BH9: Rounding / Definition Difference
A10: 45170 | B10: 4154014.5 | C10: 3373435.1 | D10: 3373435.1 | E10: 3796047.9 | F10: 813438.32 | G10: 822694.7 | H10: -455471.75 | I10: Minor Variance | J10: 12743268 | K10: 4154014.5 | L10: 3373435.1 | M10: 13523847 | N10: 0 | O10: OK | P10: 360866.05 | Q10: 619227.97 | R10: 0 | S10: 0 | T10: 0 | U10: OK | V10: 5180494.3 | W10: 3861616.9 | X10: 479682.79 | Y10: 381778.74 | Z10: 457415.93 | AA10: 531 | AB10: 531 | AC10: 9756.1098 | AD10: Control Exception | AE10: 53403824 | AF10: 828130 | AG10: 59171.52 | AH10: 22442 | AI10: 0 | AJ10: 865058.48 | AK10: 4521823.6 | AL10: 54238543 | AM10: Control Exception | AN10: 2775 | AO10: 2831 | AP10: 0 | AQ10: 62 | AR10: 0.99968651 | AS10: 1.0006878 | AT10: 0 | AU10: 0.022342342 | AV10: Control Exception | AW10: 5541360.4 | AX10: -2167925.3 | AY10: -0.6426462 | AZ10: 6352.9851 | BA10: 0.016198437 | BB10: Actual | BC10: 4519878.6 | BD10: 1945 | BE10: 54268883 | BF10: -30340 | BG10: Source Definition Difference | BH10: Rounding / Definition Difference
A11: 45200 | B11: 4065230 | C11: 3639853 | D11: 3639853 | E11: 3921672.6 | F11: 632971.96 | G11: 644302.72 | H11: -489414.58 | I11: Definition Difference | J11: 13523847 | K11: 4065230 | L11: 3639853 | M11: 13949224 | N11: 0 | O11: OK | P11: 593476.8 | Q11: 397281.74 | R11: 0 | S11: 0 | T11: 0 | U11: OK | V11: 5252380.2 | W11: 3916179.1 | X11: 485548.37 | Y11: 387643.59 | Z11: 463009.14 | AA11: 536 | AB11: 536 | AC11: 9799.2168 | AD11: Control Exception | AE11: 54268883 | AF11: 1028968 | AG11: 44596.08 | AH11: 5224 | AI11: 39600 | AJ11: 1028740.6 | AK11: 4607543.6 | AL11: 55280483 | AM11: Control Exception | AN11: 2837 | AO11: 2886 | AP11: 3 | AQ11: 58 | AR11: 0.99954441 | AS11: 0.9999958 | AT11: 0.0010574551 | AU11: 0.020444131 | AV11: Control Exception | AW11: 5845857 | AX11: -2206003.9 | AY11: -0.60606951 | AZ11: 6790.7706 | BA11: 0.018956362 | BB11: Actual | BC11: 4606707 | BD11: 836.66667 | BE11: 55297623 | BF11: -17140 | BG11: Source Definition Difference | BH11: Rounding / Definition Difference
A12: 45231 | B12: 3442796.8 | C12: 3770045.8 | D12: 3770045.8 | E12: 3229596.3 | F12: 613074.49 | G12: 620715.9 | H12: -399873.94 | I12: Definition Difference | J12: 13949224 | K12: 3442796.8 | L12: 3770045.8 | M12: 13626975 | N12: 5000 | O12: Check | P12: 592750.93 | Q12: 544597.98 | R12: 0 | S12: 0 | T12: 0 | U12: OK | V12: 5366818.2 | W12: 4001316.7 | X12: 496390.03 | Y12: 396466.42 | Z12: 472645.06 | AA12: 546 | AB12: 546 | AC12: 9829.3375 | AD12: Control Exception | AE12: 55297623 | AF12: 861511 | AG12: 42329.88 | AH12: 9923 | AI12: 14100 | AJ12: 879817 | AK12: 4680853.4 | AL12: 56160300 | AM12: Control Exception | AN12: 2893 | AO12: 2936 | AP12: 2 | AQ12: 52 | AR12: 0.99992906 | AS12: 1.0003311 | AT12: 0.00069132389 | AU12: 0.017974421 | AV12: Control Exception | AW12: 5959569.2 | AX12: -2189523.4 | AY12: -0.58076839 | AZ12: 6904.8458 | BA12: 0.015910575 | BB12: Actual | BC12: 4680025 | BD12: 828.33333 | BE12: 56177440 | BF12: -17140 | BG12: Source Definition Difference | BH12: Rounding / Definition Difference
A13: 45261 | B13: 4361648.7 | C13: 4105386.4 | D13: 4105386.4 | E13: 3925204.4 | F13: 918439 | G13: 933546.37 | H13: -481994.66 | I13: Minor Variance | J13: 13621975 | K13: 4361648.7 | L13: 4105386.4 | M13: 13878237 | N13: 0 | O13: OK | P13: 469030.83 | Q13: 654590.81 | R13: 0 | S13: 0 | T13: 0 | U13: OK | V13: 5390038.8 | W13: 4018454.5 | X13: 499717.76 | Y13: 398057.85 | Z13: 473808.73 | AA13: 552 | AB13: 552 | AC13: 9764.563 | AD13: Control Exception | AE13: 56177440 | AF13: 1442518 | AG13: 72285.48 | AH13: 48552 | AI13: 50760 | AJ13: 1415492 | AK13: 4798802.7 | AL13: 57572912 | AM13: Control Exception | AN13: 2943 | AO13: 2995 | AP13: 5 | AQ13: 64 | AR13: 0.99858997 | AS13: 0.99951891 | AT13: 0.0016989467 | AU13: 0.021746517 | AV13: Control Exception | AW13: 5859069.6 | AX13: -1753683.2 | AY13: -0.42716643 | AZ13: 7437.2942 | BA13: 0.025196804 | BB13: Actual | BC13: 4797742.7 | BD13: 1060 | BE13: 57592932 | BF13: -20020 | BG13: Source Definition Difference | BH13: Rounding / Definition Difference
... A43: 46174 | B43: 6028900.7 | C43: 5797387.9 | D43: 5797387.9 | E43: 339676.06 | F43: 6393155.4 | G43: 6393361 | H43: -703930.73 | I43: Definition Difference | J43: 21266996 | K43: 6028900.7 | L43: 5797387.9 | M43: 21498509 | N43: 0 | O43: OK | P43: 77774.25 | Q43: 75311.75 | R43: 2647064 | S43: 2068723.2 | T43: 134.23667 | U43: OK | V43: 7655791.2 | W43: 5714669.1 | X43: 711755.81 | Y43: 558714.83 | Z43: 670651.46 | AA43: 854 | AB43: 854 | AC43: 8964.6267 | AD43: Control Exception | AE43: 69290095 | AF43: 0 | AG43: 1304.76 | AH43: 0 | AI43: 6000 | AJ43: -1747089 | AK43: 5627492.2 | AL43: 67446138 | AM43: Control Exception | AN43: 3632 | AO43: 3518 | AP43: 1 | AQ43: 0 | AR43: 0.97534477 | AS43: 0.97478588 | AT43: 0.0002753304 | AU43: 0 | AV43: Control Exception | AW43: 7733565.4 | AX43: -1936177.6 | AY43: -0.33397413 | AZ43: 6788.5104 | BA43: -0.025214124 | BB43: Actual | BC43: 5620511.5 | BD43: 6980.6367 | BE43: 67543006 | BF43: -96867.64 | BG43: Source Definition Difference | BH43: Rounding / Definition Difference

Sheet 05_Monthly_Model
A1: Nexus Technologies — Monthly Financial Model
A2: Currency: GBP / Units: £ actual
A4: Month | B4: ='02_Control'!$B$8 -> 44927 | C4: =EDATE(B4,1) -> 44958 | D4: =EDATE(C4,1) -> 44986 | E4: =EDATE(D4,1) -> 45017 | F4: =EDATE(E4,1) -> 45047 | G4: =EDATE(F4,1) -> 45078 | H4: =EDATE(G4,1) -> 45108 | I4: =EDATE(H4,1) -> 45139 | J4: =EDATE(I4,1) -> 45170 | ... CG4: =EDATE(CF4,1) -> 47453
A5: Period Type | B5: =IF(B4<='02_Control'!$B$9,"Actual","Forecast") -> Actual | C5: =IF(C4<='02_Control'!$B$9,"Actual","Forecast") -> Actual | D5: =IF(D4<='02_Control'!$B$9,"Actual","Forecast") -> Actual | E5: =IF(E4<='02_Control'!$B$9,"Actual","Forecast") -> Actual | F5: =IF(F4<='02_Control'!$B$9,"Actual","Forecast") -> Actual | G5: =IF(G4<='02_Control'!$B$9,"Actual","Forecast") -> Actual | H5: =IF(H4<='02_Control'!$B$9,"Actual","Forecast") -> Actual | I5: =IF(I4<='02_Control'!$B$9,"Actual","Forecast") -> Actual | ... CG5: =IF(CG4<='02_Control'!$B$9,"Actual","Forecast") -> Forecast
A6: Calendar Year | B6: =YEAR(B4) -> 2023 | C6: =YEAR(C4) -> 2023 | D6: =YEAR(D4) -> 2023 | E6: =YEAR(E4) -> 2023 | F6: =YEAR(F4) -> 2023 | G6: =YEAR(G4) -> 2023 | H6: =YEAR(H4) -> 2023 | I6: =YEAR(I4) -> 2023 | ... CG6: =YEAR(CG4) -> 2029
A7: Quarter | B7: ="Q"&ROUNDUP(MONTH(B4)/3,0) -> Q1 | C7: ="Q"&ROUNDUP(MONTH(C4)/3,0) -> Q1 | D7: ="Q"&ROUNDUP(MONTH(D4)/3,0) -> Q1 | E7: ="Q"&ROUNDUP(MONTH(E4)/3,0) -> Q2 | F7: ="Q"&ROUNDUP(MONTH(F4)/3,0) -> Q2 | G7: ="Q"&ROUNDUP(MONTH(G4)/3,0) -> Q2 | H7: ="Q"&ROUNDUP(MONTH(H4)/3,0) -> Q3 | I7: ="Q"&ROUNDUP(MONTH(I4)/3,0) -> Q3 | ... CG7: ="Q"&ROUNDUP(MONTH(CG4)/3,0) -> Q4
A9: Revenue & ARR
A10: Recognised Revenue | B10: =IF(B$5="Actual",SUMIFS(tbl_model_feed_final[recognised_revenue_actual_gbp],tbl_model_feed_final[reporting_month_date],B$4)/'02_Control'!$B$18,"") -> 1466626.4 | C10: =IF(C$5="Actual",SUMIFS(tbl_model_feed_final[recognised_revenue_actual_gbp],tbl_model_feed_final[reporting_month_date],C$4)/'02_Control'!$B$18,"") -> 1641714.9 | D10: =IF(D$5="Actual",SUMIFS(tbl_model_feed_final[recognised_revenue_actual_gbp],tbl_model_feed_final[reporting_month_date],D$4)/'02_Control'!$B$18,"") -> 1917718.6 | E10: =IF(E$5="Actual",SUMIFS(tbl_model_feed_final[recognised_revenue_actual_gbp],tbl_model_feed_final[reporting_month_date],E$4)/'02_Control'!$B$18,"") -> 2122884.7 | F10: =IF(F$5="Actual",SUMIFS(tbl_model_feed_final[recognised_revenue_actual_gbp],tbl_model_feed_final[reporting_month_date],F$4)/'02_Control'!$B$18,"") -> 2373771 | G10: =IF(G$5="Actual",SUMIFS(tbl_model_feed_final[recognised_revenue_actual_gbp],tbl_model_feed_final[reporting_month_date],G$4)/'02_Control'!$B$18,"") -> 2624063.5 | H10: =IF(H$5="Actual",SUMIFS(tbl_model_feed_final[recognised_revenue_actual_gbp],tbl_model_feed_final[reporting_month_date],H$4)/'02_Control'!$B$18,"") -> 2899362.8 | I10: =IF(I$5="Actual",SUMIFS(tbl_model_feed_final[recognised_revenue_actual_gbp],tbl_model_feed_final[reporting_month_date],I$4)/'02_Control'!$B$18,"") -> 3163202.6 | ... AQ10: =IF(AQ$5="Actual",SUMIFS(tbl_model_feed_final[recognised_revenue_actual_gbp],tbl_model_feed_final[reporting_month_date],AQ$4)/'02_Control'!$B$18,"") -> 5797387.9 | AR10: =IF(AR$5="Actual",SUMIFS(tbl_model_feed_final[recognised_revenue_actual_gbp],tbl_model_feed_final[reporting_month_date],AR$4)/'02_Control'!$B$18,AQ10*(1+_xlfn.XLOOKUP("Recognised Revenue Growth %",tbl_assumptions[Driver],tbl_assumptions[Selected Scenario]))) -> 5855361.7 | AS10: =IF(AS$5="Actual",SUMIFS(tbl_model_feed_final[recognised_revenue_actual_gbp],tbl_model_feed_final[reporting_month_date],AS$4)/'02_Control'!$B$18,AR10*(1+_xlfn.XLOOKUP("Recognised Revenue Growth %",tbl_assumptions[Driver],tbl_assumptions[Selected Scenario]))) -> 5913915.4 | AT10: =IF(AT$5="Actual",SUMIFS(tbl_model_feed_final[recognised_revenue_actual_gbp],tbl_model_feed_final[reporting_month_date],AT$4)/'02_Control'!$B$18,AS10*(1+_xlfn.XLOOKUP("Recognised Revenue Growth %",tbl_assumptions[Driver],tbl_assumptions[Selected Scenario]))) -> 5973054.5 | AU10: =IF(AU$5="Actual",SUMIFS(tbl_model_feed_final[recognised_revenue_actual_gbp],tbl_model_feed_final[reporting_month_date],AU$4)/'02_Control'!$B$18,AT10*(1+_xlfn.XLOOKUP("Recognised Revenue Growth %",tbl_assumptions[Driver],tbl_assumptions[Selected Scenario]))) -> 6032785.1 | AV10: =IF(AV$5="Actual",SUMIFS(tbl_model_feed_final[recognised_revenue_actual_gbp],tbl_model_feed_final[reporting_month_date],AV$4)/'02_Control'!$B$18,AU10*(1+_xlfn.XLOOKUP("Recognised Revenue Growth %",tbl_assumptions[Driver],tbl_assumptions[Selected Scenario]))) -> 6093112.9 | AW10: =IF(AW$5="Actual",SUMIFS(tbl_model_feed_final[recognised_revenue_actual_gbp],tbl_model_feed_final[reporting_month_date],AW$4)/'02_Control'!$B$18,AV10*(1+_xlfn.XLOOKUP("Recognised Revenue Growth %",tbl_assumptions[Driver],tbl_assumptions[Selected Scenario]))) -> 6154044 | AX10: =IF(AX$5="Actual",SUMIFS(tbl_model_feed_final[recognised_revenue_actual_gbp],tbl_model_feed_final[reporting_month_date],AX$4)/'02_Control'!$B$18,AW10*(1+_xlfn.XLOOKUP("Recognised Revenue Growth %",tbl_assumptions[Driver],tbl_assumptions[Selected Scenario]))) -> 6215584.5 | AY10: =IF(AY$5="Actual",SUMIFS(tbl_model_feed_final[recognised_revenue_actual_gbp],tbl_model_feed_final[reporting_month_date],AY$4)/'02_Control'!$B$18,AX10*(1+_xlfn.XLOOKUP("Recognised Revenue Growth %",tbl_assumptions[Driver],tbl_assumptions[Selected Scenario]))) -> 6277740.3 | ... CG10: =IF(CG$5="Actual",SUMIFS(tbl_model_feed_final[recognised_revenue_actual_gbp],tbl_model_feed_final[reporting_month_date],CG$4)/'02_Control'!$B$18,CF10*(1+_xlfn.XLOOKUP("Recognised Revenue Growth %",tbl_assumptions[Driver],tbl_assumptions[Selected Scenario]))) -> 8805014.1
A11: Billings | B11: =IF(B$5="Actual",SUMIFS(tbl_model_feed_final[billings_gbp],tbl_model_feed_final[reporting_month_date],B$4)/'02_Control'!$B$18,"") -> 4257902.4 | C11: =IF(C$5="Actual",SUMIFS(tbl_model_feed_final[billings_gbp],tbl_model_feed_final[reporting_month_date],C$4)/'02_Control'!$B$18,"") -> 3516657.3 | D11: =IF(D$5="Actual",SUMIFS(tbl_model_feed_final[billings_gbp],tbl_model_feed_final[reporting_month_date],D$4)/'02_Control'!$B$18,"") -> 3468525.1 | E11: =IF(E$5="Actual",SUMIFS(tbl_model_feed_final[billings_gbp],tbl_model_feed_final[reporting_month_date],E$4)/'02_Control'!$B$18,"") -> 3871963.5 | F11: =IF(F$5="Actual",SUMIFS(tbl_model_feed_final[billings_gbp],tbl_model_feed_final[reporting_month_date],F$4)/'02_Control'!$B$18,"") -> 3491692.5 | G11: =IF(G$5="Actual",SUMIFS(tbl_model_feed_final[billings_gbp],tbl_model_feed_final[reporting_month_date],G$4)/'02_Control'!$B$18,"") -> 4373359.3 | H11: =IF(H$5="Actual",SUMIFS(tbl_model_feed_final[billings_gbp],tbl_model_feed_final[reporting_month_date],H$4)/'02_Control'!$B$18,"") -> 3788027.8 | I11: =IF(I$5="Actual",SUMIFS(tbl_model_feed_final[billings_gbp],tbl_model_feed_final[reporting_month_date],I$4)/'02_Control'!$B$18,"") -> 4187386.9 | ... AQ11: =IF(AQ$5="Actual",SUMIFS(tbl_model_feed_final[billings_gbp],tbl_model_feed_final[reporting_month_date],AQ$4)/'02_Control'!$B$18,"") -> 6028900.7 | AR11: =IF(AR$5="Actual",SUMIFS(tbl_model_feed_final[billings_gbp],tbl_model_feed_final[reporting_month_date],AR$4)/'02_Control'!$B$18,AQ11*(1+_xlfn.XLOOKUP("Billings Growth %",tbl_assumptions[Driver],tbl_assumptions[Selected Scenario]))) -> 6077131.9 | AS11: =IF(AS$5="Actual",SUMIFS(tbl_model_feed_final[billings_gbp],tbl_model_feed_final[reporting_month_date],AS$4)/'02_Control'!$B$18,AR11*(1+_xlfn.XLOOKUP("Billings Growth %",tbl_assumptions[Driver],tbl_assumptions[Selected Scenario]))) -> 6125749 | AT11: =IF(AT$5="Actual",SUMIFS(tbl_model_feed_final[billings_gbp],tbl_model_feed_final[reporting_month_date],AT$4)/'02_Control'!$B$18,AS11*(1+_xlfn.XLOOKUP("Billings Growth %",tbl_assumptions[Driver],tbl_assumptions[Selected Scenario]))) -> 6174755 | AU11: =IF(AU$5="Actual",SUMIFS(tbl_model_feed_final[billings_gbp],tbl_model_feed_final[reporting_month_date],AU$4)/'02_Control'!$B$18,AT11*(1+_xlfn.XLOOKUP("Billings Growth %",tbl_assumptions[Driver],tbl_assumptions[Selected Scenario]))) -> 6224153 | AV11: =IF(AV$5="Actual",SUMIFS(tbl_model_feed_final[billings_gbp],tbl_model_feed_final[reporting_month_date],AV$4)/'02_Control'!$B$18,AU11*(1+_xlfn.XLOOKUP("Billings Growth %",tbl_assumptions[Driver],tbl_assumptions[Selected Scenario]))) -> 6273946.2 | AW11: =IF(AW$5="Actual",SUMIFS(tbl_model_feed_final[billings_gbp],tbl_model_feed_final[reporting_month_date],AW$4)/'02_Control'!$B$18,AV11*(1+_xlfn.XLOOKUP("Billings Growth %",tbl_assumptions[Driver],tbl_assumptions[Selected Scenario]))) -> 6324137.8 | AX11: =IF(AX$5="Actual",SUMIFS(tbl_model_feed_final[billings_gbp],tbl_model_feed_final[reporting_month_date],AX$4)/'02_Control'!$B$18,AW11*(1+_xlfn.XLOOKUP("Billings Growth %",tbl_assumptions[Driver],tbl_assumptions[Selected Scenario]))) -> 6374730.9 | AY11: =IF(AY$5="Actual",SUMIFS(tbl_model_feed_final[billings_gbp],tbl_model_feed_final[reporting_month_date],AY$4)/'02_Control'!$B$18,AX11*(1+_xlfn.XLOOKUP("Billings Growth %",tbl_assumptions[Driver],tbl_assumptions[Selected Scenario]))) -> 6425728.8 | ... CG11: =IF(CG$5="Actual",SUMIFS(tbl_model_feed_final[billings_gbp],tbl_model_feed_final[reporting_month_date],CG$4)/'02_Control'!$B$18,CF11*(1+_xlfn.XLOOKUP("Billings Growth %",tbl_assumptions[Driver],tbl_assumptions[Selected Scenario]))) -> 8425205.1
A12: Headline ARR | B12: =IF(B$5="Actual",SUMIFS(tbl_model_feed_final[headline_arr_gbp],tbl_model_feed_final[reporting_month_date],B$4)/'02_Control'!$B$18,"") -> 44911762 | C12: =IF(C$5="Actual",SUMIFS(tbl_model_feed_final[headline_arr_gbp],tbl_model_feed_final[reporting_month_date],C$4)/'02_Control'!$B$18,"") -> 45915625 | D12: =IF(D$5="Actual",SUMIFS(tbl_model_feed_final[headline_arr_gbp],tbl_model_feed_final[reporting_month_date],D$4)/'02_Control'!$B$18,"") -> 47126866 | E12: =IF(E$5="Actual",SUMIFS(tbl_model_feed_final[headline_arr_gbp],tbl_model_feed_final[reporting_month_date],E$4)/'02_Control'!$B$18,"") -> 48120115 | F12: =IF(F$5="Actual",SUMIFS(tbl_model_feed_final[headline_arr_gbp],tbl_model_feed_final[reporting_month_date],F$4)/'02_Control'!$B$18,"") -> 49664638 | G12: =IF(G$5="Actual",SUMIFS(tbl_model_feed_final[headline_arr_gbp],tbl_model_feed_final[reporting_month_date],G$4)/'02_Control'!$B$18,"") -> 50894905 | H12: =IF(H$5="Actual",SUMIFS(tbl_model_feed_final[headline_arr_gbp],tbl_model_feed_final[reporting_month_date],H$4)/'02_Control'!$B$18,"") -> 52006801 | I12: =IF(I$5="Actual",SUMIFS(tbl_model_feed_final[headline_arr_gbp],tbl_model_feed_final[reporting_month_date],I$4)/'02_Control'!$B$18,"") -> 53373484 | ... AQ12: =IF(AQ$5="Actual",SUMIFS(tbl_model_feed_final[headline_arr_gbp],tbl_model_feed_final[reporting_month_date],AQ$4)/'02_Control'!$B$18,"") -> 67446138 | AR12: =IF(AR$5="Actual",SUMIFS(tbl_model_feed_final[headline_arr_gbp],tbl_model_feed_final[reporting_month_date],AR$4)/'02_Control'!$B$18,AQ12*(1+_xlfn.XLOOKUP("Headline ARR Growth %",tbl_assumptions[Driver],tbl_assumptions[Selected Scenario]))) -> 68053154 | AS12: =IF(AS$5="Actual",SUMIFS(tbl_model_feed_final[headline_arr_gbp],tbl_model_feed_final[reporting_month_date],AS$4)/'02_Control'!$B$18,AR12*(1+_xlfn.XLOOKUP("Headline ARR Growth %",tbl_assumptions[Driver],tbl_assumptions[Selected Scenario]))) -> 68665632 | AT12: =IF(AT$5="Actual",SUMIFS(tbl_model_feed_final[headline_arr_gbp],tbl_model_feed_final[reporting_month_date],AT$4)/'02_Control'!$B$18,AS12*(1+_xlfn.XLOOKUP("Headline ARR Growth %",tbl_assumptions[Driver],tbl_assumptions[Selected Scenario]))) -> 69283623 | AU12: =IF(AU$5="Actual",SUMIFS(tbl_model_feed_final[headline_arr_gbp],tbl_model_feed_final[reporting_month_date],AU$4)/'02_Control'!$B$18,AT12*(1+_xlfn.XLOOKUP("Headline ARR Growth %",tbl_assumptions[Driver],tbl_assumptions[Selected Scenario]))) -> 69907175 | AV12: =IF(AV$5="Actual",SUMIFS(tbl_model_feed_final[headline_arr_gbp],tbl_model_feed_final[reporting_month_date],AV$4)/'02_Control'!$B$18,AU12*(1+_xlfn.XLOOKUP("Headline ARR Growth %",tbl_assumptions[Driver],tbl_assumptions[Selected Scenario]))) -> 70536340 | AW12: =IF(AW$5="Actual",SUMIFS(tbl_model_feed_final[headline_arr_gbp],tbl_model_feed_final[reporting_month_date],AW$4)/'02_Control'!$B$18,AV12*(1+_xlfn.XLOOKUP("Headline ARR Growth %",tbl_assumptions[Driver],tbl_assumptions[Selected Scenario]))) -> 71171167 | AX12: =IF(AX$5="Actual",SUMIFS(tbl_model_feed_final[headline_arr_gbp],tbl_model_feed_final[reporting_month_date],AX$4)/'02_Control'!$B$18,AW12*(1+_xlfn.XLOOKUP("Headline ARR Growth %",tbl_assumptions[Driver],tbl_assumptions[Selected Scenario]))) -> 71811707 | AY12: =IF(AY$5="Actual",SUMIFS(tbl_model_feed_final[headline_arr_gbp],tbl_model_feed_final[reporting_month_date],AY$4)/'02_Control'!$B$18,AX12*(1+_xlfn.XLOOKUP("Headline ARR Growth %",tbl_assumptions[Driver],tbl_assumptions[Selected Scenario]))) -> 72458013 | ... CG12: =IF(CG$5="Actual",SUMIFS(tbl_model_feed_final[headline_arr_gbp],tbl_model_feed_final[reporting_month_date],CG$4)/'02_Control'!$B$18,CF12*(1+_xlfn.XLOOKUP("Headline ARR Growth %",tbl_assumptions[Driver],tbl_assumptions[Selected Scenario]))) -> 98262107
A13: Net ARR Movement | B13: =IF(B$5="Actual",SUMIFS(tbl_model_feed_final[net_arr_delta_gbp],tbl_model_feed_final[reporting_month_date],B$4)/'02_Control'!$B$18,"") -> 1126278.6 | C13: =IF(C$5="Actual",SUMIFS(tbl_model_feed_final[net_arr_delta_gbp],tbl_model_feed_final[reporting_month_date],C$4)/'02_Control'!$B$18,"") -> 1003863 | D13: =IF(D$5="Actual",SUMIFS(tbl_model_feed_final[net_arr_delta_gbp],tbl_model_feed_final[reporting_month_date],D$4)/'02_Control'!$B$18,"") -> 1211241 | E13: =IF(E$5="Actual",SUMIFS(tbl_model_feed_final[net_arr_delta_gbp],tbl_model_feed_final[reporting_month_date],E$4)/'02_Control'!$B$18,"") -> 993248.96 | F13: =IF(F$5="Actual",SUMIFS(tbl_model_feed_final[net_arr_delta_gbp],tbl_model_feed_final[reporting_month_date],F$4)/'02_Control'!$B$18,"") -> 1544522.9 | G13: =IF(G$5="Actual",SUMIFS(tbl_model_feed_final[net_arr_delta_gbp],tbl_model_feed_final[reporting_month_date],G$4)/'02_Control'!$B$18,"") -> 1230267.7 | H13: =IF(H$5="Actual",SUMIFS(tbl_model_feed_final[net_arr_delta_gbp],tbl_model_feed_final[reporting_month_date],H$4)/'02_Control'!$B$18,"") -> 1111895.4 | I13: =IF(I$5="Actual",SUMIFS(tbl_model_feed_final[net_arr_delta_gbp],tbl_model_feed_final[reporting_month_date],I$4)/'02_Control'!$B$18,"") -> 1366683.8 | ... AQ13: =IF(AQ$5="Actual",SUMIFS(tbl_model_feed_final[net_arr_delta_gbp],tbl_model_feed_final[reporting_month_date],AQ$4)/'02_Control'!$B$18,"") -> -1747089 | AR13: =IF(AR$5="Actual",SUMIFS(tbl_model_feed_final[net_arr_delta_gbp],tbl_model_feed_final[reporting_month_date],AR$4)/'02_Control'!$B$18,AR12-AQ12) -> 607015.25 | AS13: =IF(AS$5="Actual",SUMIFS(tbl_model_feed_final[net_arr_delta_gbp],tbl_model_feed_final[reporting_month_date],AS$4)/'02_Control'!$B$18,AS12-AR12) -> 612478.38 | AT13: =IF(AT$5="Actual",SUMIFS(tbl_model_feed_final[net_arr_delta_gbp],tbl_model_feed_final[reporting_month_date],AT$4)/'02_Control'!$B$18,AT12-AS12) -> 617990.69 | AU13: =IF(AU$5="Actual",SUMIFS(tbl_model_feed_final[net_arr_delta_gbp],tbl_model_feed_final[reporting_month_date],AU$4)/'02_Control'!$B$18,AU12-AT12) -> 623552.6 | AV13: =IF(AV$5="Actual",SUMIFS(tbl_model_feed_final[net_arr_delta_gbp],tbl_model_feed_final[reporting_month_date],AV$4)/'02_Control'!$B$18,AV12-AU12) -> 629164.58 | AW13: =IF(AW$5="Actual",SUMIFS(tbl_model_feed_final[net_arr_delta_gbp],tbl_model_feed_final[reporting_month_date],AW$4)/'02_Control'!$B$18,AW12-AV12) -> 634827.06 | AX13: =IF(AX$5="Actual",SUMIFS(tbl_model_feed_final[net_arr_delta_gbp],tbl_model_feed_final[reporting_month_date],AX$4)/'02_Control'!$B$18,AX12-AW12) -> 640540.5 | AY13: =IF(AY$5="Actual",SUMIFS(tbl_model_feed_final[net_arr_delta_gbp],tbl_model_feed_final[reporting_month_date],AY$4)/'02_Control'!$B$18,AY12-AX12) -> 646305.37 | ... CG13: =IF(CG$5="Actual",SUMIFS(tbl_model_feed_final[net_arr_delta_gbp],tbl_model_feed_final[reporting_month_date],CG$4)/'02_Control'!$B$18,CG12-CF12) -> 876470.72
A14: GRR | B14: =IF(B$5="Actual",SUMIFS(tbl_model_feed_final[gross_revenue_retention_rate],tbl_model_feed_final[reporting_month_date],B$4),"") -> 0.99952588 | C14: =IF(C$5="Actual",SUMIFS(tbl_model_feed_final[gross_revenue_retention_rate],tbl_model_feed_final[reporting_month_date],C$4),"") -> 0.99924324 | D14: =IF(D$5="Actual",SUMIFS(tbl_model_feed_final[gross_revenue_retention_rate],tbl_model_feed_final[reporting_month_date],D$4),"") -> 0.99959152 | E14: =IF(E$5="Actual",SUMIFS(tbl_model_feed_final[gross_revenue_retention_rate],tbl_model_feed_final[reporting_month_date],E$4),"") -> 0.9997964 | F14: =IF(F$5="Actual",SUMIFS(tbl_model_feed_final[gross_revenue_retention_rate],tbl_model_feed_final[reporting_month_date],F$4),"") -> 0.99999377 | G14: =IF(G$5="Actual",SUMIFS(tbl_model_feed_final[gross_revenue_retention_rate],tbl_model_feed_final[reporting_month_date],G$4),"") -> 0.99963441 | H14: =IF(H$5="Actual",SUMIFS(tbl_model_feed_final[gross_revenue_retention_rate],tbl_model_feed_final[reporting_month_date],H$4),"") -> 1.0001119 | I14: =IF(I$5="Actual",SUMIFS(tbl_model_feed_final[gross_revenue_retention_rate],tbl_model_feed_final[reporting_month_date],I$4),"") -> 0.998656 | ... AQ14: =IF(AQ$5="Actual",SUMIFS(tbl_model_feed_final[gross_revenue_retention_rate],tbl_model_feed_final[reporting_month_date],AQ$4),"") -> 0.97534477 | AR14: =IF(AR$5="Actual",SUMIFS(tbl_model_feed_final[gross_revenue_retention_rate],tbl_model_feed_final[reporting_month_date],AR$4),_xlfn.XLOOKUP("GRR",tbl_assumptions[Driver],tbl_assumptions[Selected Scenario])) -> 0.91 | AS14: =IF(AS$5="Actual",SUMIFS(tbl_model_feed_final[gross_revenue_retention_rate],tbl_model_feed_final[reporting_month_date],AS$4),_xlfn.XLOOKUP("GRR",tbl_assumptions[Driver],tbl_assumptions[Selected Scenario])) -> 0.91 | AT14: =IF(AT$5="Actual",SUMIFS(tbl_model_feed_final[gross_revenue_retention_rate],tbl_model_feed_final[reporting_month_date],AT$4),_xlfn.XLOOKUP("GRR",tbl_assumptions[Driver],tbl_assumptions[Selected Scenario])) -> 0.91 | AU14: =IF(AU$5="Actual",SUMIFS(tbl_model_feed_final[gross_revenue_retention_rate],tbl_model_feed_final[reporting_month_date],AU$4),_xlfn.XLOOKUP("GRR",tbl_assumptions[Driver],tbl_assumptions[Selected Scenario])) -> 0.91 | AV14: =IF(AV$5="Actual",SUMIFS(tbl_model_feed_final[gross_revenue_retention_rate],tbl_model_feed_final[reporting_month_date],AV$4),_xlfn.XLOOKUP("GRR",tbl_assumptions[Driver],tbl_assumptions[Selected Scenario])) -> 0.91 | AW14: =IF(AW$5="Actual",SUMIFS(tbl_model_feed_final[gross_revenue_retention_rate],tbl_model_feed_final[reporting_month_date],AW$4),_xlfn.XLOOKUP("GRR",tbl_assumptions[Driver],tbl_assumptions[Selected Scenario])) -> 0.91 | AX14: =IF(AX$5="Actual",SUMIFS(tbl_model_feed_final[gross_revenue_retention_rate],tbl_model_feed_final[reporting_month_date],AX$4),_xlfn.XLOOKUP("GRR",tbl_assumptions[Driver],tbl_assumptions[Selected Scenario])) -> 0.91 | AY14: =IF(AY$5="Actual",SUMIFS(tbl_model_feed_final[gross_revenue_retention_rate],tbl_model_feed_final[reporting_month_date],AY$4),_xlfn.XLOOKUP("GRR",tbl_assumptions[Driver],tbl_assumptions[Selected Scenario])) -> 0.91 | ... CG14: =IF(CG$5="Actual",SUMIFS(tbl_model_feed_final[gross_revenue_retention_rate],tbl_model_feed_final[reporting_month_date],CG$4),_xlfn.XLOOKUP("GRR",tbl_assumptions[Driver],tbl_assumptions[Selected Scenario])) -> 0.91
A15: NRR | B15: =IF(B$5="Actual",SUMIFS(tbl_model_feed_final[net_revenue_retention_rate],tbl_model_feed_final[reporting_month_date],B$4),"") -> 1.0001135 | C15: =IF(C$5="Actual",SUMIFS(tbl_model_feed_final[net_revenue_retention_rate],tbl_model_feed_final[reporting_month_date],C$4),"") -> 0.99987679 | D15: =IF(D$5="Actual",SUMIFS(tbl_model_feed_final[net_revenue_retention_rate],tbl_model_feed_final[reporting_month_date],D$4),"") -> 0.99986557 | E15: =IF(E$5="Actual",SUMIFS(tbl_model_feed_final[net_revenue_retention_rate],tbl_model_feed_final[reporting_month_date],E$4),"") -> 0.999804 | F15: =IF(F$5="Actual",SUMIFS(tbl_model_feed_final[net_revenue_retention_rate],tbl_model_feed_final[reporting_month_date],F$4),"") -> 1.0003179 | G15: =IF(G$5="Actual",SUMIFS(tbl_model_feed_final[net_revenue_retention_rate],tbl_model_feed_final[reporting_month_date],G$4),"") -> 1.0007459 | H15: =IF(H$5="Actual",SUMIFS(tbl_model_feed_final[net_revenue_retention_rate],tbl_model_feed_final[reporting_month_date],H$4),"") -> 1.0009787 | I15: =IF(I$5="Actual",SUMIFS(tbl_model_feed_final[net_revenue_retention_rate],tbl_model_feed_final[reporting_month_date],I$4),"") -> 0.99881498 | ... AQ15: =IF(AQ$5="Actual",SUMIFS(tbl_model_feed_final[net_revenue_retention_rate],tbl_model_feed_final[reporting_month_date],AQ$4),"") -> 0.97478588 | AR15: =IF(AR$5="Actual",SUMIFS(tbl_model_feed_final[net_revenue_retention_rate],tbl_model_feed_final[reporting_month_date],AR$4),_xlfn.XLOOKUP("NRR",tbl_assumptions[Driver],tbl_assumptions[Selected Scenario])) -> 1.04 | AS15: =IF(AS$5="Actual",SUMIFS(tbl_model_feed_final[net_revenue_retention_rate],tbl_model_feed_final[reporting_month_date],AS$4),_xlfn.XLOOKUP("NRR",tbl_assumptions[Driver],tbl_assumptions[Selected Scenario])) -> 1.04 | AT15: =IF(AT$5="Actual",SUMIFS(tbl_model_feed_final[net_revenue_retention_rate],tbl_model_feed_final[reporting_month_date],AT$4),_xlfn.XLOOKUP("NRR",tbl_assumptions[Driver],tbl_assumptions[Selected Scenario])) -> 1.04 | AU15: =IF(AU$5="Actual",SUMIFS(tbl_model_feed_final[net_revenue_retention_rate],tbl_model_feed_final[reporting_month_date],AU$4),_xlfn.XLOOKUP("NRR",tbl_assumptions[Driver],tbl_assumptions[Selected Scenario])) -> 1.04 | AV15: =IF(AV$5="Actual",SUMIFS(tbl_model_feed_final[net_revenue_retention_rate],tbl_model_feed_final[reporting_month_date],AV$4),_xlfn.XLOOKUP("NRR",tbl_assumptions[Driver],tbl_assumptions[Selected Scenario])) -> 1.04 | AW15: =IF(AW$5="Actual",SUMIFS(tbl_model_feed_final[net_revenue_retention_rate],tbl_model_feed_final[reporting_month_date],AW$4),_xlfn.XLOOKUP("NRR",tbl_assumptions[Driver],tbl_assumptions[Selected Scenario])) -> 1.04 | AX15: =IF(AX$5="Actual",SUMIFS(tbl_model_feed_final[net_revenue_retention_rate],tbl_model_feed_final[reporting_month_date],AX$4),_xlfn.XLOOKUP("NRR",tbl_assumptions[Driver],tbl_assumptions[Selected Scenario])) -> 1.04 | AY15: =IF(AY$5="Actual",SUMIFS(tbl_model_feed_final[net_revenue_retention_rate],tbl_model_feed_final[reporting_month_date],AY$4),_xlfn.XLOOKUP("NRR",tbl_assumptions[Driver],tbl_assumptions[Selected Scenario])) -> 1.04 | ... CG15: =IF(CG$5="Actual",SUMIFS(tbl_model_feed_final[net_revenue_retention_rate],tbl_model_feed_final[reporting_month_date],CG$4),_xlfn.XLOOKUP("NRR",tbl_assumptions[Driver],tbl_assumptions[Selected Scenario])) -> 1.04
A16: Logo Churn | B16: =IF(B$5="Actual",SUMIFS(tbl_model_feed_final[logo_churn_rate],tbl_model_feed_final[reporting_month_date],B$4),"") -> 0.00043994721 | C16: =IF(C$5="Actual",SUMIFS(tbl_model_feed_final[logo_churn_rate],tbl_model_feed_final[reporting_month_date],C$4),"") -> 0.00085910653 | D16: =IF(D$5="Actual",SUMIFS(tbl_model_feed_final[logo_churn_rate],tbl_model_feed_final[reporting_month_date],D$4),"") -> 0.00083927822 | E16: =IF(E$5="Actual",SUMIFS(tbl_model_feed_final[logo_churn_rate],tbl_model_feed_final[reporting_month_date],E$4),"") -> 0 | F16: =IF(F$5="Actual",SUMIFS(tbl_model_feed_final[logo_churn_rate],tbl_model_feed_final[reporting_month_date],F$4),"") -> 0.00039761431 | G16: =IF(G$5="Actual",SUMIFS(tbl_model_feed_final[logo_churn_rate],tbl_model_feed_final[reporting_month_date],G$4),"") -> 0.00038520801 | H16: =IF(H$5="Actual",SUMIFS(tbl_model_feed_final[logo_churn_rate],tbl_model_feed_final[reporting_month_date],H$4),"") -> 0 | I16: =IF(I$5="Actual",SUMIFS(tbl_model_feed_final[logo_churn_rate],tbl_model_feed_final[reporting_month_date],I$4),"") -> 0.00073855244 | ... AQ16: =IF(AQ$5="Actual",SUMIFS(tbl_model_feed_final[logo_churn_rate],tbl_model_feed_final[reporting_month_date],AQ$4),"") -> 0.0002753304 | AR16: =IF(AR$5="Actual",SUMIFS(tbl_model_feed_final[logo_churn_rate],tbl_model_feed_final[reporting_month_date],AR$4),_xlfn.XLOOKUP("Logo Churn",tbl_assumptions[Driver],tbl_assumptions[Selected Scenario])) -> 0.018 | AS16: =IF(AS$5="Actual",SUMIFS(tbl_model_feed_final[logo_churn_rate],tbl_model_feed_final[reporting_month_date],AS$4),_xlfn.XLOOKUP("Logo Churn",tbl_assumptions[Driver],tbl_assumptions[Selected Scenario])) -> 0.018 | AT16: =IF(AT$5="Actual",SUMIFS(tbl_model_feed_final[logo_churn_rate],tbl_model_feed_final[reporting_month_date],AT$4),_xlfn.XLOOKUP("Logo Churn",tbl_assumptions[Driver],tbl_assumptions[Selected Scenario])) -> 0.018 | AU16: =IF(AU$5="Actual",SUMIFS(tbl_model_feed_final[logo_churn_rate],tbl_model_feed_final[reporting_month_date],AU$4),_xlfn.XLOOKUP("Logo Churn",tbl_assumptions[Driver],tbl_assumptions[Selected Scenario])) -> 0.018 | AV16: =IF(AV$5="Actual",SUMIFS(tbl_model_feed_final[logo_churn_rate],tbl_model_feed_final[reporting_month_date],AV$4),_xlfn.XLOOKUP("Logo Churn",tbl_assumptions[Driver],tbl_assumptions[Selected Scenario])) -> 0.018 | AW16: =IF(AW$5="Actual",SUMIFS(tbl_model_feed_final[logo_churn_rate],tbl_model_feed_final[reporting_month_date],AW$4),_xlfn.XLOOKUP("Logo Churn",tbl_assumptions[Driver],tbl_assumptions[Selected Scenario])) -> 0.018 | AX16: =IF(AX$5="Actual",SUMIFS(tbl_model_feed_final[logo_churn_rate],tbl_model_feed_final[reporting_month_date],AX$4),_xlfn.XLOOKUP("Logo Churn",tbl_assumptions[Driver],tbl_assumptions[Selected Scenario])) -> 0.018 | AY16: =IF(AY$5="Actual",SUMIFS(tbl_model_feed_final[logo_churn_rate],tbl_model_feed_final[reporting_month_date],AY$4),_xlfn.XLOOKUP("Logo Churn",tbl_assumptions[Driver],tbl_assumptions[Selected Scenario])) -> 0.018 | ... CG16: =IF(CG$5="Actual",SUMIFS(tbl_model_feed_final[logo_churn_rate],tbl_model_feed_final[reporting_month_date],CG$4),_xlfn.XLOOKUP("Logo Churn",tbl_assumptions[Driver],tbl_assumptions[Selected Scenario])) -> 0.018
A18: Operating Costs
A19: Payroll Cost | B19: =IF(B$5="Actual",SUMIFS(tbl_model_feed_final[payroll_cost_gbp],tbl_model_feed_final[reporting_month_date],B$4)/'02_Control'!$B$18,"") -> 4641129.1 | C19: =IF(C$5="Actual",SUMIFS(tbl_model_feed_final[payroll_cost_gbp],tbl_model_feed_final[reporting_month_date],C$4)/'02_Control'!$B$18,"") -> 4731102.6 | D19: =IF(D$5="Actual",SUMIFS(tbl_model_feed_final[payroll_cost_gbp],tbl_model_feed_final[reporting_month_date],D$4)/'02_Control'!$B$18,"") -> 4807431.4 | E19: =IF(E$5="Actual",SUMIFS(tbl_model_feed_final[payroll_cost_gbp],tbl_model_feed_final[reporting_month_date],E$4)/'02_Control'!$B$18,"") -> 4868707.2 | F19: =IF(F$5="Actual",SUMIFS(tbl_model_feed_final[payroll_cost_gbp],tbl_model_feed_final[reporting_month_date],F$4)/'02_Control'!$B$18,"") -> 4929130.6 | G19: =IF(G$5="Actual",SUMIFS(tbl_model_feed_final[payroll_cost_gbp],tbl_model_feed_final[reporting_month_date],G$4)/'02_Control'!$B$18,"") -> 4974433.4 | H19: =IF(H$5="Actual",SUMIFS(tbl_model_feed_final[payroll_cost_gbp],tbl_model_feed_final[reporting_month_date],H$4)/'02_Control'!$B$18,"") -> 5078537 | I19: =IF(I$5="Actual",SUMIFS(tbl_model_feed_final[payroll_cost_gbp],tbl_model_feed_final[reporting_month_date],I$4)/'02_Control'!$B$18,"") -> 5101870.2 | ... AQ19: =IF(AQ$5="Actual",SUMIFS(tbl_model_feed_final[payroll_cost_gbp],tbl_model_feed_final[reporting_month_date],AQ$4)/'02_Control'!$B$18,"") -> 7655791.2 | AR19: =IF(AR$5="Actual",SUMIFS(tbl_model_feed_final[payroll_cost_gbp],tbl_model_feed_final[reporting_month_date],AR$4)/'02_Control'!$B$18,AQ19*(1+_xlfn.XLOOKUP("Payroll Growth %",tbl_assumptions[Driver],tbl_assumptions[Selected Scenario]))) -> 7732349.1 | AS19: =IF(AS$5="Actual",SUMIFS(tbl_model_feed_final[payroll_cost_gbp],tbl_model_feed_final[reporting_month_date],AS$4)/'02_Control'!$B$18,AR19*(1+_xlfn.XLOOKUP("Payroll Growth %",tbl_assumptions[Driver],tbl_assumptions[Selected Scenario]))) -> 7809672.6 | AT19: =IF(AT$5="Actual",SUMIFS(tbl_model_feed_final[payroll_cost_gbp],tbl_model_feed_final[reporting_month_date],AT$4)/'02_Control'!$B$18,AS19*(1+_xlfn.XLOOKUP("Payroll Growth %",tbl_assumptions[Driver],tbl_assumptions[Selected Scenario]))) -> 7887769.3 | AU19: =IF(AU$5="Actual",SUMIFS(tbl_model_feed_final[payroll_cost_gbp],tbl_model_feed_final[reporting_month_date],AU$4)/'02_Control'!$B$18,AT19*(1+_xlfn.XLOOKUP("Payroll Growth %",tbl_assumptions[Driver],tbl_assumptions[Selected Scenario]))) -> 7966647 | AV19: =IF(AV$5="Actual",SUMIFS(tbl_model_feed_final[payroll_cost_gbp],tbl_model_feed_final[reporting_month_date],AV$4)/'02_Control'!$B$18,AU19*(1+_xlfn.XLOOKUP("Payroll Growth %",tbl_assumptions[Driver],tbl_assumptions[Selected Scenario]))) -> 8046313.5 | AW19: =IF(AW$5="Actual",SUMIFS(tbl_model_feed_final[payroll_cost_gbp],tbl_model_feed_final[reporting_month_date],AW$4)/'02_Control'!$B$18,AV19*(1+_xlfn.XLOOKUP("Payroll Growth %",tbl_assumptions[Driver],tbl_assumptions[Selected Scenario]))) -> 8126776.6 | AX19: =IF(AX$5="Actual",SUMIFS(tbl_model_feed_final[payroll_cost_gbp],tbl_model_feed_final[reporting_month_date],AX$4)/'02_Control'!$B$18,AW19*(1+_xlfn.XLOOKUP("Payroll Growth %",tbl_assumptions[Driver],tbl_assumptions[Selected Scenario]))) -> 8208044.4 | AY19: =IF(AY$5="Actual",SUMIFS(tbl_model_feed_final[payroll_cost_gbp],tbl_model_feed_final[reporting_month_date],AY$4)/'02_Control'!$B$18,AX19*(1+_xlfn.XLOOKUP("Payroll Growth %",tbl_assumptions[Driver],tbl_assumptions[Selected Scenario]))) -> 8290124.8 | ... CG19: =IF(CG$5="Actual",SUMIFS(tbl_model_feed_final[payroll_cost_gbp],tbl_model_feed_final[reporting_month_date],CG$4)/'02_Control'!$B$18,CF19*(1+_xlfn.XLOOKUP("Payroll Growth %",tbl_assumptions[Driver],tbl_assumptions[Selected Scenario]))) -> 11627538
A20: AP Invoice Spend | B20: =IF(B$5="Actual",SUMIFS(tbl_model_feed_final[ap_invoice_spend_gbp],tbl_model_feed_final[reporting_month_date],B$4)/'02_Control'!$B$18,"") -> 291150.19 | C20: =IF(C$5="Actual",SUMIFS(tbl_model_feed_final[ap_invoice_spend_gbp],tbl_model_feed_final[reporting_month_date],C$4)/'02_Control'!$B$18,"") -> 658218.22 | D20: =IF(D$5="Actual",SUMIFS(tbl_model_feed_final[ap_invoice_spend_gbp],tbl_model_feed_final[reporting_month_date],D$4)/'02_Control'!$B$18,"") -> 560331.15 | E20: =IF(E$5="Actual",SUMIFS(tbl_model_feed_final[ap_invoice_spend_gbp],tbl_model_feed_final[reporting_month_date],E$4)/'02_Control'!$B$18,"") -> 755499.01 | F20: =IF(F$5="Actual",SUMIFS(tbl_model_feed_final[ap_invoice_spend_gbp],tbl_model_feed_final[reporting_month_date],F$4)/'02_Control'!$B$18,"") -> 519926.93 | G20: =IF(G$5="Actual",SUMIFS(tbl_model_feed_final[ap_invoice_spend_gbp],tbl_model_feed_final[reporting_month_date],G$4)/'02_Control'!$B$18,"") -> 679161.62 | H20: =IF(H$5="Actual",SUMIFS(tbl_model_feed_final[ap_invoice_spend_gbp],tbl_model_feed_final[reporting_month_date],H$4)/'02_Control'!$B$18,"") -> 588706.85 | I20: =IF(I$5="Actual",SUMIFS(tbl_model_feed_final[ap_invoice_spend_gbp],tbl_model_feed_final[reporting_month_date],I$4)/'02_Control'!$B$18,"") -> 863983.56 | ... AQ20: =IF(AQ$5="Actual",SUMIFS(tbl_model_feed_final[ap_invoice_spend_gbp],tbl_model_feed_final[reporting_month_date],AQ$4)/'02_Control'!$B$18,"") -> 77774.25 | AR20: =IF(AR$5="Actual",SUMIFS(tbl_model_feed_final[ap_invoice_spend_gbp],tbl_model_feed_final[reporting_month_date],AR$4)/'02_Control'!$B$18,AQ20*(1+_xlfn.XLOOKUP("AP Spend Growth %",tbl_assumptions[Driver],tbl_assumptions[Selected Scenario]))) -> 78396.444 | AS20: =IF(AS$5="Actual",SUMIFS(tbl_model_feed_final[ap_invoice_spend_gbp],tbl_model_feed_final[reporting_month_date],AS$4)/'02_Control'!$B$18,AR20*(1+_xlfn.XLOOKUP("AP Spend Growth %",tbl_assumptions[Driver],tbl_assumptions[Selected Scenario]))) -> 79023.616 | AT20: =IF(AT$5="Actual",SUMIFS(tbl_model_feed_final[ap_invoice_spend_gbp],tbl_model_feed_final[reporting_month_date],AT$4)/'02_Control'!$B$18,AS20*(1+_xlfn.XLOOKUP("AP Spend Growth %",tbl_assumptions[Driver],tbl_assumptions[Selected Scenario]))) -> 79655.804 | AU20: =IF(AU$5="Actual",SUMIFS(tbl_model_feed_final[ap_invoice_spend_gbp],tbl_model_feed_final[reporting_month_date],AU$4)/'02_Control'!$B$18,AT20*(1+_xlfn.XLOOKUP("AP Spend Growth %",tbl_assumptions[Driver],tbl_assumptions[Selected Scenario]))) -> 80293.051 | AV20: =IF(AV$5="Actual",SUMIFS(tbl_model_feed_final[ap_invoice_spend_gbp],tbl_model_feed_final[reporting_month_date],AV$4)/'02_Control'!$B$18,AU20*(1+_xlfn.XLOOKUP("AP Spend Growth %",tbl_assumptions[Driver],tbl_assumptions[Selected Scenario]))) -> 80935.395 | AW20: =IF(AW$5="Actual",SUMIFS(tbl_model_feed_final[ap_invoice_spend_gbp],tbl_model_feed_final[reporting_month_date],AW$4)/'02_Control'!$B$18,AV20*(1+_xlfn.XLOOKUP("AP Spend Growth %",tbl_assumptions[Driver],tbl_assumptions[Selected Scenario]))) -> 81582.878 | AX20: =IF(AX$5="Actual",SUMIFS(tbl_model_feed_final[ap_invoice_spend_gbp],tbl_model_feed_final[reporting_month_date],AX$4)/'02_Control'!$B$18,AW20*(1+_xlfn.XLOOKUP("AP Spend Growth %",tbl_assumptions[Driver],tbl_assumptions[Selected Scenario]))) -> 82235.542 | AY20: =IF(AY$5="Actual",SUMIFS(tbl_model_feed_final[ap_invoice_spend_gbp],tbl_model_feed_final[reporting_month_date],AY$4)/'02_Control'!$B$18,AX20*(1+_xlfn.XLOOKUP("AP Spend Growth %",tbl_assumptions[Driver],tbl_assumptions[Selected Scenario]))) -> 82893.426 | ... CG20: =IF(CG$5="Actual",SUMIFS(tbl_model_feed_final[ap_invoice_spend_gbp],tbl_model_feed_final[reporting_month_date],CG$4)/'02_Control'!$B$18,CF20*(1+_xlfn.XLOOKUP("AP Spend Growth %",tbl_assumptions[Driver],tbl_assumptions[Selected Scenario]))) -> 108687.14
A21: Operating Expense Proxy | B21: =IF(B$5="Actual",SUMIFS(tbl_model_feed_final[actual_operating_expense_gbp],tbl_model_feed_final[reporting_month_date],B$4)/'02_Control'!$B$18,"") -> 4932279.3 | C21: =IF(C$5="Actual",SUMIFS(tbl_model_feed_final[actual_operating_expense_gbp],tbl_model_feed_final[reporting_month_date],C$4)/'02_Control'!$B$18,"") -> 5389320.9 | D21: =IF(D$5="Actual",SUMIFS(tbl_model_feed_final[actual_operating_expense_gbp],tbl_model_feed_final[reporting_month_date],D$4)/'02_Control'!$B$18,"") -> 5367762.6 | E21: =IF(E$5="Actual",SUMIFS(tbl_model_feed_final[actual_operating_expense_gbp],tbl_model_feed_final[reporting_month_date],E$4)/'02_Control'!$B$18,"") -> 5624206.2 | F21: =IF(F$5="Actual",SUMIFS(tbl_model_feed_final[actual_operating_expense_gbp],tbl_model_feed_final[reporting_month_date],F$4)/'02_Control'!$B$18,"") -> 5449057.5 | G21: =IF(G$5="Actual",SUMIFS(tbl_model_feed_final[actual_operating_expense_gbp],tbl_model_feed_final[reporting_month_date],G$4)/'02_Control'!$B$18,"") -> 5653595 | H21: =IF(H$5="Actual",SUMIFS(tbl_model_feed_final[actual_operating_expense_gbp],tbl_model_feed_final[reporting_month_date],H$4)/'02_Control'!$B$18,"") -> 5667243.8 | I21: =IF(I$5="Actual",SUMIFS(tbl_model_feed_final[actual_operating_expense_gbp],tbl_model_feed_final[reporting_month_date],I$4)/'02_Control'!$B$18,"") -> 5965853.7 | ... AQ21: =IF(AQ$5="Actual",SUMIFS(tbl_model_feed_final[actual_operating_expense_gbp],tbl_model_feed_final[reporting_month_date],AQ$4)/'02_Control'!$B$18,"") -> 7733565.4 | AR21: =IF(AR$5="Actual",SUMIFS(tbl_model_feed_final[actual_operating_expense_gbp],tbl_model_feed_final[reporting_month_date],AR$4)/'02_Control'!$B$18,AR19+AR20) -> 7810745.5 | AS21: =IF(AS$5="Actual",SUMIFS(tbl_model_feed_final[actual_operating_expense_gbp],tbl_model_feed_final[reporting_month_date],AS$4)/'02_Control'!$B$18,AS19+AS20) -> 7888696.2 | AT21: =IF(AT$5="Actual",SUMIFS(tbl_model_feed_final[actual_operating_expense_gbp],tbl_model_feed_final[reporting_month_date],AT$4)/'02_Control'!$B$18,AT19+AT20) -> 7967425.1 | AU21: =IF(AU$5="Actual",SUMIFS(tbl_model_feed_final[actual_operating_expense_gbp],tbl_model_feed_final[reporting_month_date],AU$4)/'02_Control'!$B$18,AU19+AU20) -> 8046940.1 | AV21: =IF(AV$5="Actual",SUMIFS(tbl_model_feed_final[actual_operating_expense_gbp],tbl_model_feed_final[reporting_month_date],AV$4)/'02_Control'!$B$18,AV19+AV20) -> 8127248.9 | AW21: =IF(AW$5="Actual",SUMIFS(tbl_model_feed_final[actual_operating_expense_gbp],tbl_model_feed_final[reporting_month_date],AW$4)/'02_Control'!$B$18,AW19+AW20) -> 8208359.5 | AX21: =IF(AX$5="Actual",SUMIFS(tbl_model_feed_final[actual_operating_expense_gbp],tbl_model_feed_final[reporting_month_date],AX$4)/'02_Control'!$B$18,AX19+AX20) -> 8290279.9 | AY21: =IF(AY$5="Actual",SUMIFS(tbl_model_feed_final[actual_operating_expense_gbp],tbl_model_feed_final[reporting_month_date],AY$4)/'02_Control'!$B$18,AY19+AY20) -> 8373018.2 | ... CG21: =IF(CG$5="Actual",SUMIFS(tbl_model_feed_final[actual_operating_expense_gbp],tbl_model_feed_final[reporting_month_date],CG$4)/'02_Control'!$B$18,CG19+CG20) -> 11736225
A22: Operating expense proxy check | B22: =IF(B$5="Actual",B19+B20-B21,0) -> 0 | C22: =IF(C$5="Actual",C19+C20-C21,0) -> 0 | D22: =IF(D$5="Actual",D19+D20-D21,0) -> 0 | E22: =IF(E$5="Actual",E19+E20-E21,0) -> 0 | F22: =IF(F$5="Actual",F19+F20-F21,0) -> 0 | G22: =IF(G$5="Actual",G19+G20-G21,0) -> 0 | H22: =IF(H$5="Actual",H19+H20-H21,0) -> 0 | I22: =IF(I$5="Actual",I19+I20-I21,0) -> 0 | ... AQ22: =IF(AQ$5="Actual",AQ19+AQ20-AQ21,0) -> 0 | AR22: =IF(AQ$5="Actual",AQ19+AQ20-AQ21,0) -> 0 | AS22: =IF(AR$5="Actual",AR19+AR20-AR21,0) -> 0 | AT22: =IF(AS$5="Actual",AS19+AS20-AS21,0) -> 0 | AU22: =IF(AT$5="Actual",AT19+AT20-AT21,0) -> 0 | AV22: =IF(AU$5="Actual",AU19+AU20-AU21,0) -> 0 | AW22: =IF(AV$5="Actual",AV19+AV20-AV21,0) -> 0 | AX22: =IF(AW$5="Actual",AW19+AW20-AW21,0) -> 0 | AY22: =IF(AX$5="Actual",AX19+AX20-AX21,0) -> 0 | ... CG22: =IF(CF$5="Actual",CF19+CF20-CF21,0) -> 0
A23: Operating Profit | B23: =IF(B$5="Actual",SUMIFS(tbl_model_feed_final[actual_operating_profit_gbp],tbl_model_feed_final[reporting_month_date],B$4)/'02_Control'!$B$18,"") -> -3465652.9 | C23: =IF(C$5="Actual",SUMIFS(tbl_model_feed_final[actual_operating_profit_gbp],tbl_model_feed_final[reporting_month_date],C$4)/'02_Control'!$B$18,"") -> -3747605.9 | D23: =IF(D$5="Actual",SUMIFS(tbl_model_feed_final[actual_operating_profit_gbp],tbl_model_feed_final[reporting_month_date],D$4)/'02_Control'!$B$18,"") -> -3450043.9 | E23: =IF(E$5="Actual",SUMIFS(tbl_model_feed_final[actual_operating_profit_gbp],tbl_model_feed_final[reporting_month_date],E$4)/'02_Control'!$B$18,"") -> -3501321.5 | F23: =IF(F$5="Actual",SUMIFS(tbl_model_feed_final[actual_operating_profit_gbp],tbl_model_feed_final[reporting_month_date],F$4)/'02_Control'!$B$18,"") -> -3075286.5 | G23: =IF(G$5="Actual",SUMIFS(tbl_model_feed_final[actual_operating_profit_gbp],tbl_model_feed_final[reporting_month_date],G$4)/'02_Control'!$B$18,"") -> -3029531.5 | H23: =IF(H$5="Actual",SUMIFS(tbl_model_feed_final[actual_operating_profit_gbp],tbl_model_feed_final[reporting_month_date],H$4)/'02_Control'!$B$18,"") -> -2767881 | I23: =IF(I$5="Actual",SUMIFS(tbl_model_feed_final[actual_operating_profit_gbp],tbl_model_feed_final[reporting_month_date],I$4)/'02_Control'!$B$18,"") -> -2802651.1 | ... AQ23: =IF(AQ$5="Actual",SUMIFS(tbl_model_feed_final[actual_operating_profit_gbp],tbl_model_feed_final[reporting_month_date],AQ$4)/'02_Control'!$B$18,"") -> -1936177.6 | AR23: =IF(AR$5="Actual",SUMIFS(tbl_model_feed_final[actual_operating_profit_gbp],tbl_model_feed_final[reporting_month_date],AR$4)/'02_Control'!$B$18,AR10-AR21) -> -1955383.8 | AS23: =IF(AS$5="Actual",SUMIFS(tbl_model_feed_final[actual_operating_profit_gbp],tbl_model_feed_final[reporting_month_date],AS$4)/'02_Control'!$B$18,AS10-AS21) -> -1974780.8 | AT23: =IF(AT$5="Actual",SUMIFS(tbl_model_feed_final[actual_operating_profit_gbp],tbl_model_feed_final[reporting_month_date],AT$4)/'02_Control'!$B$18,AT10-AT21) -> -1994370.6 | AU23: =IF(AU$5="Actual",SUMIFS(tbl_model_feed_final[actual_operating_profit_gbp],tbl_model_feed_final[reporting_month_date],AU$4)/'02_Control'!$B$18,AU10-AU21) -> -2014155 | AV23: =IF(AV$5="Actual",SUMIFS(tbl_model_feed_final[actual_operating_profit_gbp],tbl_model_feed_final[reporting_month_date],AV$4)/'02_Control'!$B$18,AV10-AV21) -> -2034136 | AW23: =IF(AW$5="Actual",SUMIFS(tbl_model_feed_final[actual_operating_profit_gbp],tbl_model_feed_final[reporting_month_date],AW$4)/'02_Control'!$B$18,AW10-AW21) -> -2054315.5 | AX23: =IF(AX$5="Actual",SUMIFS(tbl_model_feed_final[actual_operating_profit_gbp],tbl_model_feed_final[reporting_month_date],AX$4)/'02_Control'!$B$18,AX10-AX21) -> -2074695.4 | AY23: =IF(AY$5="Actual",SUMIFS(tbl_model_feed_final[actual_operating_profit_gbp],tbl_model_feed_final[reporting_month_date],AY$4)/'02_Control'!$B$18,AY10-AY21) -> -2095277.9 | ... CG23: =IF(CG$5="Actual",SUMIFS(tbl_model_feed_final[actual_operating_profit_gbp],tbl_model_feed_final[reporting_month_date],CG$4)/'02_Control'!$B$18,CG10-CG21) -> -2931211.3
A24: Operating Profit Check | B24: =IF(B$5="Actual",B10-B21-B23,0) -> 0 | C24: =IF(C$5="Actual",C10-C21-C23,0) -> 0 | D24: =IF(D$5="Actual",D10-D21-D23,0) -> 0 | E24: =IF(E$5="Actual",E10-E21-E23,0) -> 0 | F24: =IF(F$5="Actual",F10-F21-F23,0) -> 0 | G24: =IF(G$5="Actual",G10-G21-G23,0) -> 0 | H24: =IF(H$5="Actual",H10-H21-H23,0) -> 0 | I24: =IF(I$5="Actual",I10-I21-I23,0) -> 0 | ... CG24: =IF(CG$5="Actual",CG10-CG21-CG23,0) -> 0
A25: Operating Margin | B25: =IF(B$5="Actual",SUMIFS(tbl_model_feed_final[actual_operating_margin],tbl_model_feed_final[reporting_month_date],B$4),"") -> -2.36301 | C25: =IF(C$5="Actual",SUMIFS(tbl_model_feed_final[actual_operating_margin],tbl_model_feed_final[reporting_month_date],C$4),"") -> -2.2827385 | D25: =IF(D$5="Actual",SUMIFS(tbl_model_feed_final[actual_operating_margin],tbl_model_feed_final[reporting_month_date],D$4),"") -> -1.7990355 | E25: =IF(E$5="Actual",SUMIFS(tbl_model_feed_final[actual_operating_margin],tbl_model_feed_final[reporting_month_date],E$4),"") -> -1.6493225 | F25: =IF(F$5="Actual",SUMIFS(tbl_model_feed_final[actual_operating_margin],tbl_model_feed_final[reporting_month_date],F$4),"") -> -1.2955279 | G25: =IF(G$5="Actual",SUMIFS(tbl_model_feed_final[actual_operating_margin],tbl_model_feed_final[reporting_month_date],G$4),"") -> -1.1545191 | H25: =IF(H$5="Actual",SUMIFS(tbl_model_feed_final[actual_operating_margin],tbl_model_feed_final[reporting_month_date],H$4),"") -> -0.95465151 | I25: =IF(I$5="Actual",SUMIFS(tbl_model_feed_final[actual_operating_margin],tbl_model_feed_final[reporting_month_date],I$4),"") -> -0.88601695 | ... AQ25: =IF(AQ$5="Actual",SUMIFS(tbl_model_feed_final[actual_operating_margin],tbl_model_feed_final[reporting_month_date],AQ$4),"") -> -0.33397413 | AR25: =IFERROR(AR23/AR10,"") -> -0.33394757 | AS25: =IFERROR(AS23/AS10,"") -> -0.33392105 | AT25: =IFERROR(AT23/AT10,"") -> -0.33389459 | AU25: =IFERROR(AU23/AU10,"") -> -0.33386819 | AV25: =IFERROR(AV23/AV10,"") -> -0.33384183 | AW25: =IFERROR(AW23/AW10,"") -> -0.33381553 | AX25: =IFERROR(AX23/AX10,"") -> -0.33378928 | AY25: =IFERROR(AY23/AY10,"") -> -0.33376308 | ... CG25: =IFERROR(CG23/CG10,"") -> -0.33290251
A26: Active FTE | B26: =IF(B$5="Actual",SUMIFS(tbl_model_feed_final[active_fte_count],tbl_model_feed_final[reporting_month_date],B$4),"") -> 452 | C26: =IF(C$5="Actual",SUMIFS(tbl_model_feed_final[active_fte_count],tbl_model_feed_final[reporting_month_date],C$4),"") -> 461 | D26: =IF(D$5="Actual",SUMIFS(tbl_model_feed_final[active_fte_count],tbl_model_feed_final[reporting_month_date],D$4),"") -> 476 | E26: =IF(E$5="Actual",SUMIFS(tbl_model_feed_final[active_fte_count],tbl_model_feed_final[reporting_month_date],E$4),"") -> 487 | F26: =IF(F$5="Actual",SUMIFS(tbl_model_feed_final[active_fte_count],tbl_model_feed_final[reporting_month_date],F$4),"") -> 496 | G26: =IF(G$5="Actual",SUMIFS(tbl_model_feed_final[active_fte_count],tbl_model_feed_final[reporting_month_date],G$4),"") -> 505 | H26: =IF(H$5="Actual",SUMIFS(tbl_model_feed_final[active_fte_count],tbl_model_feed_final[reporting_month_date],H$4),"") -> 513 | I26: =IF(I$5="Actual",SUMIFS(tbl_model_feed_final[active_fte_count],tbl_model_feed_final[reporting_month_date],I$4),"") -> 520 | ... AQ26: =IF(AQ$5="Actual",SUMIFS(tbl_model_feed_final[active_fte_count],tbl_model_feed_final[reporting_month_date],AQ$4),"") -> 854 | AR26: =IF(AR$5="Actual",SUMIFS(tbl_model_feed_final[active_fte_count],tbl_model_feed_final[reporting_month_date],AR$4),AQ26*(1+_xlfn.XLOOKUP("FTE Growth %",tbl_assumptions[Driver],tbl_assumptions[Selected Scenario]))) -> 859.124 | AS26: =IF(AS$5="Actual",SUMIFS(tbl_model_feed_final[active_fte_count],tbl_model_feed_final[reporting_month_date],AS$4),AR26*(1+_xlfn.XLOOKUP("FTE Growth %",tbl_assumptions[Driver],tbl_assumptions[Selected Scenario]))) -> 864.27874 | AT26: =IF(AT$5="Actual",SUMIFS(tbl_model_feed_final[active_fte_count],tbl_model_feed_final[reporting_month_date],AT$4),AS26*(1+_xlfn.XLOOKUP("FTE Growth %",tbl_assumptions[Driver],tbl_assumptions[Selected Scenario]))) -> 869.46442 | AU26: =IF(AU$5="Actual",SUMIFS(tbl_model_feed_final[active_fte_count],tbl_model_feed_final[reporting_month_date],AU$4),AT26*(1+_xlfn.XLOOKUP("FTE Growth %",tbl_assumptions[Driver],tbl_assumptions[Selected Scenario]))) -> 874.6812 | AV26: =IF(AV$5="Actual",SUMIFS(tbl_model_feed_final[active_fte_count],tbl_model_feed_final[reporting_month_date],AV$4),AU26*(1+_xlfn.XLOOKUP("FTE Growth %",tbl_assumptions[Driver],tbl_assumptions[Selected Scenario]))) -> 879.92929 | AW26: =IF(AW$5="Actual",SUMIFS(tbl_model_feed_final[active_fte_count],tbl_model_feed_final[reporting_month_date],AW$4),AV26*(1+_xlfn.XLOOKUP("FTE Growth %",tbl_assumptions[Driver],tbl_assumptions[Selected Scenario]))) -> 885.20887 | AX26: =IF(AX$5="Actual",SUMIFS(tbl_model_feed_final[active_fte_count],tbl_model_feed_final[reporting_month_date],AX$4),AW26*(1+_xlfn.XLOOKUP("FTE Growth %",tbl_assumptions[Driver],tbl_assumptions[Selected Scenario]))) -> 890.52012 | AY26: =IF(AY$5="Actual",SUMIFS(tbl_model_feed_final[active_fte_count],tbl_model_feed_final[reporting_month_date],AY$4),AX26*(1+_xlfn.XLOOKUP("FTE Growth %",tbl_assumptions[Driver],tbl_assumptions[Selected Scenario]))) -> 895.86324 | ... CG26: =IF(CG$5="Actual",SUMIFS(tbl_model_feed_final[active_fte_count],tbl_model_feed_final[reporting_month_date],CG$4),CF26*(1+_xlfn.XLOOKUP("FTE Growth %",tbl_assumptions[Driver],tbl_assumptions[Selected Scenario]))) -> 1097.926
A27: Revenue per Active FTE | B27: =IF(B$5="Actual",SUMIFS(tbl_model_feed_final[revenue_per_active_fte_gbp],tbl_model_feed_final[reporting_month_date],B$4)/'02_Control'!$B$18,"") -> 3244.7487 | C27: =IF(C$5="Actual",SUMIFS(tbl_model_feed_final[revenue_per_active_fte_gbp],tbl_model_feed_final[reporting_month_date],C$4)/'02_Control'!$B$18,"") -> 3561.2038 | D27: =IF(D$5="Actual",SUMIFS(tbl_model_feed_final[revenue_per_active_fte_gbp],tbl_model_feed_final[reporting_month_date],D$4)/'02_Control'!$B$18,"") -> 4028.8207 | E27: =IF(E$5="Actual",SUMIFS(tbl_model_feed_final[revenue_per_active_fte_gbp],tbl_model_feed_final[reporting_month_date],E$4)/'02_Control'!$B$18,"") -> 4359.1062 | F27: =IF(F$5="Actual",SUMIFS(tbl_model_feed_final[revenue_per_active_fte_gbp],tbl_model_feed_final[reporting_month_date],F$4)/'02_Control'!$B$18,"") -> 4785.8286 | G27: =IF(G$5="Actual",SUMIFS(tbl_model_feed_final[revenue_per_active_fte_gbp],tbl_model_feed_final[reporting_month_date],G$4)/'02_Control'!$B$18,"") -> 5196.1654 | H27: =IF(H$5="Actual",SUMIFS(tbl_model_feed_final[revenue_per_active_fte_gbp],tbl_model_feed_final[reporting_month_date],H$4)/'02_Control'!$B$18,"") -> 5651.7793 | I27: =IF(I$5="Actual",SUMIFS(tbl_model_feed_final[revenue_per_active_fte_gbp],tbl_model_feed_final[reporting_month_date],I$4)/'02_Control'!$B$18,"") -> 6083.0819 | ... AQ27: =IF(AQ$5="Actual",SUMIFS(tbl_model_feed_final[revenue_per_active_fte_gbp],tbl_model_feed_final[reporting_month_date],AQ$4)/'02_Control'!$B$18,"") -> 6788.5104 | AR27: =IFERROR(AR10/AR26,"") -> 6815.5025 | AS27: =IFERROR(AS10/AS26,"") -> 6842.6019 | AT27: =IFERROR(AT10/AT26,"") -> 6869.809 | AU27: =IFERROR(AU10/AU26,"") -> 6897.1244 | AV27: =IFERROR(AV10/AV26,"") -> 6924.5483 | AW27: =IFERROR(AW10/AW26,"") -> 6952.0813 | AX27: =IFERROR(AX10/AX26,"") -> 6979.7238 | AY27: =IFERROR(AY10/AY26,"") -> 7007.4762 | ... CG27: =IFERROR(CG10/CG26,"") -> 8019.6792
A29: Working Capital
A30: Cash Collected | B30: =IF(B$5="Actual",SUMIFS(tbl_model_feed_final[cash_collected_gbp],tbl_model_feed_final[reporting_month_date],B$4)/'02_Control'!$B$18,"") -> 3771182.3 | C30: =IF(C$5="Actual",SUMIFS(tbl_model_feed_final[cash_collected_gbp],tbl_model_feed_final[reporting_month_date],C$4)/'02_Control'!$B$18,"") -> 3312454.7 | D30: =IF(D$5="Actual",SUMIFS(tbl_model_feed_final[cash_collected_gbp],tbl_model_feed_final[reporting_month_date],D$4)/'02_Control'!$B$18,"") -> 3172057.9 | E30: =IF(E$5="Actual",SUMIFS(tbl_model_feed_final[cash_collected_gbp],tbl_model_feed_final[reporting_month_date],E$4)/'02_Control'!$B$18,"") -> 3613516.5 | F30: =IF(F$5="Actual",SUMIFS(tbl_model_feed_final[cash_collected_gbp],tbl_model_feed_final[reporting_month_date],F$4)/'02_Control'!$B$18,"") -> 3000694 | G30: =IF(G$5="Actual",SUMIFS(tbl_model_feed_final[cash_collected_gbp],tbl_model_feed_final[reporting_month_date],G$4)/'02_Control'!$B$18,"") -> 3983097.2 | H30: =IF(H$5="Actual",SUMIFS(tbl_model_feed_final[cash_collected_gbp],tbl_model_feed_final[reporting_month_date],H$4)/'02_Control'!$B$18,"") -> 3687227.4 | I30: =IF(I$5="Actual",SUMIFS(tbl_model_feed_final[cash_collected_gbp],tbl_model_feed_final[reporting_month_date],I$4)/'02_Control'!$B$18,"") -> 4042353.8 | ... AQ30: =IF(AQ$5="Actual",SUMIFS(tbl_model_feed_final[cash_collected_gbp],tbl_model_feed_final[reporting_month_date],AQ$4)/'02_Control'!$B$18,"") -> 339676.06 | AR30: =IF(AR$5="Actual",SUMIFS(tbl_model_feed_final[cash_collected_gbp],tbl_model_feed_final[reporting_month_date],AR$4)/'02_Control'!$B$18,AR11*_xlfn.XLOOKUP("Cash Collection % of Billings",tbl_assumptions[Driver],tbl_assumptions[Selected Scenario])) -> 4983248.2 | AS30: =IF(AS$5="Actual",SUMIFS(tbl_model_feed_final[cash_collected_gbp],tbl_model_feed_final[reporting_month_date],AS$4)/'02_Control'!$B$18,AS11*_xlfn.XLOOKUP("Cash Collection % of Billings",tbl_assumptions[Driver],tbl_assumptions[Selected Scenario])) -> 5023114.2 | AT30: =IF(AT$5="Actual",SUMIFS(tbl_model_feed_final[cash_collected_gbp],tbl_model_feed_final[reporting_month_date],AT$4)/'02_Control'!$B$18,AT11*_xlfn.XLOOKUP("Cash Collection % of Billings",tbl_assumptions[Driver],tbl_assumptions[Selected Scenario])) -> 5063299.1 | AU30: =IF(AU$5="Actual",SUMIFS(tbl_model_feed_final[cash_collected_gbp],tbl_model_feed_final[reporting_month_date],AU$4)/'02_Control'!$B$18,AU11*_xlfn.XLOOKUP("Cash Collection % of Billings",tbl_assumptions[Driver],tbl_assumptions[Selected Scenario])) -> 5103805.5 | AV30: =IF(AV$5="Actual",SUMIFS(tbl_model_feed_final[cash_collected_gbp],tbl_model_feed_final[reporting_month_date],AV$4)/'02_Control'!$B$18,AV11*_xlfn.XLOOKUP("Cash Collection % of Billings",tbl_assumptions[Driver],tbl_assumptions[Selected Scenario])) -> 5144635.9 | AW30: =IF(AW$5="Actual",SUMIFS(tbl_model_feed_final[cash_collected_gbp],tbl_model_feed_final[reporting_month_date],AW$4)/'02_Control'!$B$18,AW11*_xlfn.XLOOKUP("Cash Collection % of Billings",tbl_assumptions[Driver],tbl_assumptions[Selected Scenario])) -> 5185793 | AX30: =IF(AX$5="Actual",SUMIFS(tbl_model_feed_final[cash_collected_gbp],tbl_model_feed_final[reporting_month_date],AX$4)/'02_Control'!$B$18,AX11*_xlfn.XLOOKUP("Cash Collection % of Billings",tbl_assumptions[Driver],tbl_assumptions[Selected Scenario])) -> 5227279.4 | AY30: =IF(AY$5="Actual",SUMIFS(tbl_model_feed_final[cash_collected_gbp],tbl_model_feed_final[reporting_month_date],AY$4)/'02_Control'!$B$18,AY11*_xlfn.XLOOKUP("Cash Collection % of Billings",tbl_assumptions[Driver],tbl_assumptions[Selected Scenario])) -> 5269097.6 | ... CG30: =IF(CG$5="Actual",SUMIFS(tbl_model_feed_final[cash_collected_gbp],tbl_model_feed_final[reporting_month_date],CG$4)/'02_Control'!$B$18,CG11*_xlfn.XLOOKUP("Cash Collection % of Billings",tbl_assumptions[Driver],tbl_assumptions[Selected Scenario])) -> 6908668.2
A31: Open AR Exposure | B31: =IF(B$5="Actual",SUMIFS(tbl_model_feed_final[open_ar_exposure_gbp],tbl_model_feed_final[reporting_month_date],B$4)/'02_Control'!$B$18,"") -> 1073080.8 | C31: =IF(C$5="Actual",SUMIFS(tbl_model_feed_final[open_ar_exposure_gbp],tbl_model_feed_final[reporting_month_date],C$4)/'02_Control'!$B$18,"") -> 584121.35 | D31: =IF(D$5="Actual",SUMIFS(tbl_model_feed_final[open_ar_exposure_gbp],tbl_model_feed_final[reporting_month_date],D$4)/'02_Control'!$B$18,"") -> 740587.59 | E31: =IF(E$5="Actual",SUMIFS(tbl_model_feed_final[open_ar_exposure_gbp],tbl_model_feed_final[reporting_month_date],E$4)/'02_Control'!$B$18,"") -> 720385.8 | F31: =IF(F$5="Actual",SUMIFS(tbl_model_feed_final[open_ar_exposure_gbp],tbl_model_feed_final[reporting_month_date],F$4)/'02_Control'!$B$18,"") -> 848665.75 | G31: =IF(G$5="Actual",SUMIFS(tbl_model_feed_final[open_ar_exposure_gbp],tbl_model_feed_final[reporting_month_date],G$4)/'02_Control'!$B$18,"") -> 917567.49 | H31: =IF(H$5="Actual",SUMIFS(tbl_model_feed_final[open_ar_exposure_gbp],tbl_model_feed_final[reporting_month_date],H$4)/'02_Control'!$B$18,"") -> 557672.58 | I31: =IF(I$5="Actual",SUMIFS(tbl_model_feed_final[open_ar_exposure_gbp],tbl_model_feed_final[reporting_month_date],I$4)/'02_Control'!$B$18,"") -> 648072.02 | ... AQ31: =IF(AQ$5="Actual",SUMIFS(tbl_model_feed_final[open_ar_exposure_gbp],tbl_model_feed_final[reporting_month_date],AQ$4)/'02_Control'!$B$18,"") -> 6393361 | AR31: =IF(AR$5="Actual",SUMIFS(tbl_model_feed_final[open_ar_exposure_gbp],tbl_model_feed_final[reporting_month_date],AR$4)/'02_Control'!$B$18,AR11*_xlfn.XLOOKUP("Open AR % of Billings",tbl_assumptions[Driver],tbl_assumptions[Selected Scenario])) -> 911569.79 | AS31: =IF(AS$5="Actual",SUMIFS(tbl_model_feed_final[open_ar_exposure_gbp],tbl_model_feed_final[reporting_month_date],AS$4)/'02_Control'!$B$18,AS11*_xlfn.XLOOKUP("Open AR % of Billings",tbl_assumptions[Driver],tbl_assumptions[Selected Scenario])) -> 918862.35 | AT31: =IF(AT$5="Actual",SUMIFS(tbl_model_feed_final[open_ar_exposure_gbp],tbl_model_feed_final[reporting_month_date],AT$4)/'02_Control'!$B$18,AT11*_xlfn.XLOOKUP("Open AR % of Billings",tbl_assumptions[Driver],tbl_assumptions[Selected Scenario])) -> 926213.25 | AU31: =IF(AU$5="Actual",SUMIFS(tbl_model_feed_final[open_ar_exposure_gbp],tbl_model_feed_final[reporting_month_date],AU$4)/'02_Control'!$B$18,AU11*_xlfn.XLOOKUP("Open AR % of Billings",tbl_assumptions[Driver],tbl_assumptions[Selected Scenario])) -> 933622.95 | AV31: =IF(AV$5="Actual",SUMIFS(tbl_model_feed_final[open_ar_exposure_gbp],tbl_model_feed_final[reporting_month_date],AV$4)/'02_Control'!$B$18,AV11*_xlfn.XLOOKUP("Open AR % of Billings",tbl_assumptions[Driver],tbl_assumptions[Selected Scenario])) -> 941091.94 | AW31: =IF(AW$5="Actual",SUMIFS(tbl_model_feed_final[open_ar_exposure_gbp],tbl_model_feed_final[reporting_month_date],AW$4)/'02_Control'!$B$18,AW11*_xlfn.XLOOKUP("Open AR % of Billings",tbl_assumptions[Driver],tbl_assumptions[Selected Scenario])) -> 948620.67 | AX31: =IF(AX$5="Actual",SUMIFS(tbl_model_feed_final[open_ar_exposure_gbp],tbl_model_feed_final[reporting_month_date],AX$4)/'02_Control'!$B$18,AX11*_xlfn.XLOOKUP("Open AR % of Billings",tbl_assumptions[Driver],tbl_assumptions[Selected Scenario])) -> 956209.64 | AY31: =IF(AY$5="Actual",SUMIFS(tbl_model_feed_final[open_ar_exposure_gbp],tbl_model_feed_final[reporting_month_date],AY$4)/'02_Control'!$B$18,AY11*_xlfn.XLOOKUP("Open AR % of Billings",tbl_assumptions[Driver],tbl_assumptions[Selected Scenario])) -> 963859.32 | ... CG31: =IF(CG$5="Actual",SUMIFS(tbl_model_feed_final[open_ar_exposure_gbp],tbl_model_feed_final[reporting_month_date],CG$4)/'02_Control'!$B$18,CG11*_xlfn.XLOOKUP("Open AR % of Billings",tbl_assumptions[Driver],tbl_assumptions[Selected Scenario])) -> 1263780.8
A32: Open AP Liability | B32: =IF(B$5="Actual",SUMIFS(tbl_model_feed_final[open_ap_liability_gbp],tbl_model_feed_final[reporting_month_date],B$4)/'02_Control'!$B$18,"") -> 0 | C32: =IF(C$5="Actual",SUMIFS(tbl_model_feed_final[open_ap_liability_gbp],tbl_model_feed_final[reporting_month_date],C$4)/'02_Control'!$B$18,"") -> 0 | D32: =IF(D$5="Actual",SUMIFS(tbl_model_feed_final[open_ap_liability_gbp],tbl_model_feed_final[reporting_month_date],D$4)/'02_Control'!$B$18,"") -> 0 | E32: =IF(E$5="Actual",SUMIFS(tbl_model_feed_final[open_ap_liability_gbp],tbl_model_feed_final[reporting_month_date],E$4)/'02_Control'!$B$18,"") -> 0 | F32: =IF(F$5="Actual",SUMIFS(tbl_model_feed_final[open_ap_liability_gbp],tbl_model_feed_final[reporting_month_date],F$4)/'02_Control'!$B$18,"") -> 0 | G32: =IF(G$5="Actual",SUMIFS(tbl_model_feed_final[open_ap_liability_gbp],tbl_model_feed_final[reporting_month_date],G$4)/'02_Control'!$B$18,"") -> 0 | H32: =IF(H$5="Actual",SUMIFS(tbl_model_feed_final[open_ap_liability_gbp],tbl_model_feed_final[reporting_month_date],H$4)/'02_Control'!$B$18,"") -> 0 | I32: =IF(I$5="Actual",SUMIFS(tbl_model_feed_final[open_ap_liability_gbp],tbl_model_feed_final[reporting_month_date],I$4)/'02_Control'!$B$18,"") -> 0 | ... AQ32: =IF(AQ$5="Actual",SUMIFS(tbl_model_feed_final[open_ap_liability_gbp],tbl_model_feed_final[reporting_month_date],AQ$4)/'02_Control'!$B$18,"") -> 2647064 | AR32: =IF(AR$5="Actual",SUMIFS(tbl_model_feed_final[open_ap_liability_gbp],tbl_model_feed_final[reporting_month_date],AR$4)/'02_Control'!$B$18,AR20*_xlfn.XLOOKUP("Open AP % of AP Spend",tbl_assumptions[Driver],tbl_assumptions[Selected Scenario])) -> 9407.5733 | AS32: =IF(AS$5="Actual",SUMIFS(tbl_model_feed_final[open_ap_liability_gbp],tbl_model_feed_final[reporting_month_date],AS$4)/'02_Control'!$B$18,AS20*_xlfn.XLOOKUP("Open AP % of AP Spend",tbl_assumptions[Driver],tbl_assumptions[Selected Scenario])) -> 9482.8339 | AT32: =IF(AT$5="Actual",SUMIFS(tbl_model_feed_final[open_ap_liability_gbp],tbl_model_feed_final[reporting_month_date],AT$4)/'02_Control'!$B$18,AT20*_xlfn.XLOOKUP("Open AP % of AP Spend",tbl_assumptions[Driver],tbl_assumptions[Selected Scenario])) -> 9558.6965 | AU32: =IF(AU$5="Actual",SUMIFS(tbl_model_feed_final[open_ap_liability_gbp],tbl_model_feed_final[reporting_month_date],AU$4)/'02_Control'!$B$18,AU20*_xlfn.XLOOKUP("Open AP % of AP Spend",tbl_assumptions[Driver],tbl_assumptions[Selected Scenario])) -> 9635.1661 | AV32: =IF(AV$5="Actual",SUMIFS(tbl_model_feed_final[open_ap_liability_gbp],tbl_model_feed_final[reporting_month_date],AV$4)/'02_Control'!$B$18,AV20*_xlfn.XLOOKUP("Open AP % of AP Spend",tbl_assumptions[Driver],tbl_assumptions[Selected Scenario])) -> 9712.2474 | AW32: =IF(AW$5="Actual",SUMIFS(tbl_model_feed_final[open_ap_liability_gbp],tbl_model_feed_final[reporting_month_date],AW$4)/'02_Control'!$B$18,AW20*_xlfn.XLOOKUP("Open AP % of AP Spend",tbl_assumptions[Driver],tbl_assumptions[Selected Scenario])) -> 9789.9454 | AX32: =IF(AX$5="Actual",SUMIFS(tbl_model_feed_final[open_ap_liability_gbp],tbl_model_feed_final[reporting_month_date],AX$4)/'02_Control'!$B$18,AX20*_xlfn.XLOOKUP("Open AP % of AP Spend",tbl_assumptions[Driver],tbl_assumptions[Selected Scenario])) -> 9868.265 | AY32: =IF(AY$5="Actual",SUMIFS(tbl_model_feed_final[open_ap_liability_gbp],tbl_model_feed_final[reporting_month_date],AY$4)/'02_Control'!$B$18,AY20*_xlfn.XLOOKUP("Open AP % of AP Spend",tbl_assumptions[Driver],tbl_assumptions[Selected Scenario])) -> 9947.2111 | ... CG32: =IF(CG$5="Actual",SUMIFS(tbl_model_feed_final[open_ap_liability_gbp],tbl_model_feed_final[reporting_month_date],CG$4)/'02_Control'!$B$18,CG20*_xlfn.XLOOKUP("Open AP % of AP Spend",tbl_assumptions[Driver],tbl_assumptions[Selected Scenario])) -> 13042.457
A33: Closing Deferred Revenue | B33: =IF(B$5="Actual",SUMIFS(tbl_model_feed_final[closing_deferred_revenue_gbp],tbl_model_feed_final[reporting_month_date],B$4)/'02_Control'!$B$18,"") -> 2788373.4 | C33: =IF(C$5="Actual",SUMIFS(tbl_model_feed_final[closing_deferred_revenue_gbp],tbl_model_feed_final[reporting_month_date],C$4)/'02_Control'!$B$18,"") -> 4663315.8 | D33: =IF(D$5="Actual",SUMIFS(tbl_model_feed_final[closing_deferred_revenue_gbp],tbl_model_feed_final[reporting_month_date],D$4)/'02_Control'!$B$18,"") -> 6214122.3 | E33: =IF(E$5="Actual",SUMIFS(tbl_model_feed_final[closing_deferred_revenue_gbp],tbl_model_feed_final[reporting_month_date],E$4)/'02_Control'!$B$18,"") -> 7963201 | F33: =IF(F$5="Actual",SUMIFS(tbl_model_feed_final[closing_deferred_revenue_gbp],tbl_model_feed_final[reporting_month_date],F$4)/'02_Control'!$B$18,"") -> 9081122.6 | G33: =IF(G$5="Actual",SUMIFS(tbl_model_feed_final[closing_deferred_revenue_gbp],tbl_model_feed_final[reporting_month_date],G$4)/'02_Control'!$B$18,"") -> 10830418 | H33: =IF(H$5="Actual",SUMIFS(tbl_model_feed_final[closing_deferred_revenue_gbp],tbl_model_feed_final[reporting_month_date],H$4)/'02_Control'!$B$18,"") -> 11719083 | I33: =IF(I$5="Actual",SUMIFS(tbl_model_feed_final[closing_deferred_revenue_gbp],tbl_model_feed_final[reporting_month_date],I$4)/'02_Control'!$B$18,"") -> 12743268 | ... AQ33: =IF(AQ$5="Actual",SUMIFS(tbl_model_feed_final[closing_deferred_revenue_gbp],tbl_model_feed_final[reporting_month_date],AQ$4)/'02_Control'!$B$18,"") -> 21498509 | AR33: =IF(AR$5="Actual",SUMIFS(tbl_model_feed_final[closing_deferred_revenue_gbp],tbl_model_feed_final[reporting_month_date],AR$4)/'02_Control'!$B$18,AR11*_xlfn.XLOOKUP("Deferred Revenue % of Billings",tbl_assumptions[Driver],tbl_assumptions[Selected Scenario])) -> 4861705.5 | AS33: =IF(AS$5="Actual",SUMIFS(tbl_model_feed_final[closing_deferred_revenue_gbp],tbl_model_feed_final[reporting_month_date],AS$4)/'02_Control'!$B$18,AS11*_xlfn.XLOOKUP("Deferred Revenue % of Billings",tbl_assumptions[Driver],tbl_assumptions[Selected Scenario])) -> 4900599.2 | AT33: =IF(AT$5="Actual",SUMIFS(tbl_model_feed_final[closing_deferred_revenue_gbp],tbl_model_feed_final[reporting_month_date],AT$4)/'02_Control'!$B$18,AT11*_xlfn.XLOOKUP("Deferred Revenue % of Billings",tbl_assumptions[Driver],tbl_assumptions[Selected Scenario])) -> 4939804 | AU33: =IF(AU$5="Actual",SUMIFS(tbl_model_feed_final[closing_deferred_revenue_gbp],tbl_model_feed_final[reporting_month_date],AU$4)/'02_Control'!$B$18,AU11*_xlfn.XLOOKUP("Deferred Revenue % of Billings",tbl_assumptions[Driver],tbl_assumptions[Selected Scenario])) -> 4979322.4 | AV33: =IF(AV$5="Actual",SUMIFS(tbl_model_feed_final[closing_deferred_revenue_gbp],tbl_model_feed_final[reporting_month_date],AV$4)/'02_Control'!$B$18,AV11*_xlfn.XLOOKUP("Deferred Revenue % of Billings",tbl_assumptions[Driver],tbl_assumptions[Selected Scenario])) -> 5019157 | AW33: =IF(AW$5="Actual",SUMIFS(tbl_model_feed_final[closing_deferred_revenue_gbp],tbl_model_feed_final[reporting_month_date],AW$4)/'02_Control'!$B$18,AW11*_xlfn.XLOOKUP("Deferred Revenue % of Billings",tbl_assumptions[Driver],tbl_assumptions[Selected Scenario])) -> 5059310.3 | AX33: =IF(AX$5="Actual",SUMIFS(tbl_model_feed_final[closing_deferred_revenue_gbp],tbl_model_feed_final[reporting_month_date],AX$4)/'02_Control'!$B$18,AX11*_xlfn.XLOOKUP("Deferred Revenue % of Billings",tbl_assumptions[Driver],tbl_assumptions[Selected Scenario])) -> 5099784.7 | AY33: =IF(AY$5="Actual",SUMIFS(tbl_model_feed_final[closing_deferred_revenue_gbp],tbl_model_feed_final[reporting_month_date],AY$4)/'02_Control'!$B$18,AY11*_xlfn.XLOOKUP("Deferred Revenue % of Billings",tbl_assumptions[Driver],tbl_assumptions[Selected Scenario])) -> 5140583 | ... CG33: =IF(CG$5="Actual",SUMIFS(tbl_model_feed_final[closing_deferred_revenue_gbp],tbl_model_feed_final[reporting_month_date],CG$4)/'02_Control'!$B$18,CG11*_xlfn.XLOOKUP("Deferred Revenue % of Billings",tbl_assumptions[Driver],tbl_assumptions[Selected Scenario])) -> 6740164.1
A34: Supplier Cash Paid | B34: =IF(B$5="Actual",SUMIFS(tbl_model_feed_final[supplier_cash_paid_gbp],tbl_model_feed_final[reporting_month_date],B$4)/'02_Control'!$B$18,"") -> 2972.29 | C34: =IF(C$5="Actual",SUMIFS(tbl_model_feed_final[supplier_cash_paid_gbp],tbl_model_feed_final[reporting_month_date],C$4)/'02_Control'!$B$18,"") -> 144978.52 | D34: =IF(D$5="Actual",SUMIFS(tbl_model_feed_final[supplier_cash_paid_gbp],tbl_model_feed_final[reporting_month_date],D$4)/'02_Control'!$B$18,"") -> 806474.41 | E34: =IF(E$5="Actual",SUMIFS(tbl_model_feed_final[supplier_cash_paid_gbp],tbl_model_feed_final[reporting_month_date],E$4)/'02_Control'!$B$18,"") -> 446431.7 | F34: =IF(F$5="Actual",SUMIFS(tbl_model_feed_final[supplier_cash_paid_gbp],tbl_model_feed_final[reporting_month_date],F$4)/'02_Control'!$B$18,"") -> 642419.77 | G34: =IF(G$5="Actual",SUMIFS(tbl_model_feed_final[supplier_cash_paid_gbp],tbl_model_feed_final[reporting_month_date],G$4)/'02_Control'!$B$18,"") -> 500315.7 | H34: =IF(H$5="Actual",SUMIFS(tbl_model_feed_final[supplier_cash_paid_gbp],tbl_model_feed_final[reporting_month_date],H$4)/'02_Control'!$B$18,"") -> 641704.78 | I34: =IF(I$5="Actual",SUMIFS(tbl_model_feed_final[supplier_cash_paid_gbp],tbl_model_feed_final[reporting_month_date],I$4)/'02_Control'!$B$18,"") -> 635031.87 | ... AQ34: =IF(AQ$5="Actual",SUMIFS(tbl_model_feed_final[supplier_cash_paid_gbp],tbl_model_feed_final[reporting_month_date],AQ$4)/'02_Control'!$B$18,"") -> 75311.75 | AR34: =IF(AR$5="Actual",SUMIFS(tbl_model_feed_final[supplier_cash_paid_gbp],tbl_model_feed_final[reporting_month_date],AR$4)/'02_Control'!$B$18,AR20*_xlfn.XLOOKUP("Supplier Payment % of AP Spend",tbl_assumptions[Driver],tbl_assumptions[Selected Scenario])) -> 66636.977 | AS34: =IF(AS$5="Actual",SUMIFS(tbl_model_feed_final[supplier_cash_paid_gbp],tbl_model_feed_final[reporting_month_date],AS$4)/'02_Control'!$B$18,AS20*_xlfn.XLOOKUP("Supplier Payment % of AP Spend",tbl_assumptions[Driver],tbl_assumptions[Selected Scenario])) -> 67170.073 | AT34: =IF(AT$5="Actual",SUMIFS(tbl_model_feed_final[supplier_cash_paid_gbp],tbl_model_feed_final[reporting_month_date],AT$4)/'02_Control'!$B$18,AT20*_xlfn.XLOOKUP("Supplier Payment % of AP Spend",tbl_assumptions[Driver],tbl_assumptions[Selected Scenario])) -> 67707.434 | AU34: =IF(AU$5="Actual",SUMIFS(tbl_model_feed_final[supplier_cash_paid_gbp],tbl_model_feed_final[reporting_month_date],AU$4)/'02_Control'!$B$18,AU20*_xlfn.XLOOKUP("Supplier Payment % of AP Spend",tbl_assumptions[Driver],tbl_assumptions[Selected Scenario])) -> 68249.093 | AV34: =IF(AV$5="Actual",SUMIFS(tbl_model_feed_final[supplier_cash_paid_gbp],tbl_model_feed_final[reporting_month_date],AV$4)/'02_Control'!$B$18,AV20*_xlfn.XLOOKUP("Supplier Payment % of AP Spend",tbl_assumptions[Driver],tbl_assumptions[Selected Scenario])) -> 68795.086 | AW34: =IF(AW$5="Actual",SUMIFS(tbl_model_feed_final[supplier_cash_paid_gbp],tbl_model_feed_final[reporting_month_date],AW$4)/'02_Control'!$B$18,AW20*_xlfn.XLOOKUP("Supplier Payment % of AP Spend",tbl_assumptions[Driver],tbl_assumptions[Selected Scenario])) -> 69345.447 | AX34: =IF(AX$5="Actual",SUMIFS(tbl_model_feed_final[supplier_cash_paid_gbp],tbl_model_feed_final[reporting_month_date],AX$4)/'02_Control'!$B$18,AX20*_xlfn.XLOOKUP("Supplier Payment % of AP Spend",tbl_assumptions[Driver],tbl_assumptions[Selected Scenario])) -> 69900.21 | AY34: =IF(AY$5="Actual",SUMIFS(tbl_model_feed_final[supplier_cash_paid_gbp],tbl_model_feed_final[reporting_month_date],AY$4)/'02_Control'!$B$18,AY20*_xlfn.XLOOKUP("Supplier Payment % of AP Spend",tbl_assumptions[Driver],tbl_assumptions[Selected Scenario])) -> 70459.412 | ... CG34: =IF(CG$5="Actual",SUMIFS(tbl_model_feed_final[supplier_cash_paid_gbp],tbl_model_feed_final[reporting_month_date],CG$4)/'02_Control'!$B$18,CG20*_xlfn.XLOOKUP("Supplier Payment % of AP Spend",tbl_assumptions[Driver],tbl_assumptions[Selected Scenario])) -> 92384.073

Sheet 06_Assumptions
A1: Nexus Technologies — Forecast Assumptions
A3: =CONCATENATE("Scenario selected"," = ", '02_Control'!$B$14) -> Scenario selected = Base
A5: Category | B5: Driver | C5: Downside | D5: Base | E5: Upside | F5: Selected Scenario | G5: Note
A6: Revenue & SaaS Growth | B6: Recognised Revenue Growth % | C6: 0.005 | D6: 0.01 | E6: 0.015 | F6: =CHOOSE(MATCH('02_Control'!$B$14,{"Downside","Base","Upside"},0),C6,D6,E6) -> 0.01 | G6: Monthly growth applied to recognised revenue forecast.
A7: Revenue & SaaS Growth | B7: Billings Growth % | C7: 0.003 | D7: 0.008 | E7: 0.013 | F7: =CHOOSE(MATCH('02_Control'!$B$14,{"Downside","Base","Upside"},0),C7,D7,E7) -> 0.008 | G7: Monthly growth applied to billings forecast.
A8: Revenue & SaaS Growth | B8: Headline ARR Growth % | C8: 0.004 | D8: 0.009 | E8: 0.014 | F8: =CHOOSE(MATCH('02_Control'!$B$14,{"Downside","Base","Upside"},0),C8,D8,E8) -> 0.009 | G8: Used to forecast headline ARR directly due to ARR bridge source-definition issue.
A9: Revenue & SaaS Growth | B9: GRR | C9: 0.88 | D9: 0.91 | E9: 0.94 | F9: =CHOOSE(MATCH('02_Control'!$B$14,{"Downside","Base","Upside"},0),C9,D9,E9) -> 0.91 | G9: Forecast gross revenue retention assumption.
A10: Revenue & SaaS Growth | B10: NRR | C10: 0.98 | D10: 1.04 | E10: 1.1 | F10: =CHOOSE(MATCH('02_Control'!$B$14,{"Downside","Base","Upside"},0),C10,D10,E10) -> 1.04 | G10: Forecast net revenue retention assumption.
A11: Revenue & SaaS Growth | B11: Logo Churn | C11: 0.025 | D11: 0.018 | E11: 0.012 | F11: =CHOOSE(MATCH('02_Control'!$B$14,{"Downside","Base","Upside"},0),C11,D11,E11) -> 0.018 | G11: Forecast monthly customer churn assumption.
A12: Operating Cost Drivers | B12: Payroll Growth % | C12: 0.008 | D12: 0.01 | E12: 0.013 | F12: =CHOOSE(MATCH('02_Control'!$B$14,{"Downside","Base","Upside"},0),C12,D12,E12) -> 0.01 | G12: Monthly payroll cost growth.
A13: Operating Cost Drivers | B13: AP Spend Growth % | C13: 0.005 | D13: 0.008 | E13: 0.011 | F13: =CHOOSE(MATCH('02_Control'!$B$14,{"Downside","Base","Upside"},0),C13,D13,E13) -> 0.008 | G13: Monthly vendor/AP spend growth.
A14: Operating Cost Drivers | B14: FTE Growth % | C14: 0.003 | D14: 0.006 | E14: 0.01 | F14: =CHOOSE(MATCH('02_Control'!$B$14,{"Downside","Base","Upside"},0),C14,D14,E14) -> 0.006 | G14: Monthly active FTE growth.
A15: Working Capital Drivers | B15: Cash Collection % of Billings | C15: 0.78 | D15: 0.82 | E15: 0.86 | F15: =CHOOSE(MATCH('02_Control'!$B$14,{"Downside","Base","Upside"},0),C15,D15,E15) -> 0.82 | G15: Cash collected as percentage of monthly billings.
A16: Working Capital Drivers | B16: Open AR % of Billings | C16: 0.18 | D16: 0.15 | E16: 0.12 | F16: =CHOOSE(MATCH('02_Control'!$B$14,{"Downside","Base","Upside"},0),C16,D16,E16) -> 0.15 | G16: Ending AR exposure as percentage of monthly billings.
A17: Working Capital Drivers | B17: Open AP % of AP Spend | C17: 0.1 | D17: 0.12 | E17: 0.14 | F17: =CHOOSE(MATCH('02_Control'!$B$14,{"Downside","Base","Upside"},0),C17,D17,E17) -> 0.12 | G17: Ending AP liability as percentage of monthly AP spend.
... A25: DCF Drivers | B25: Mid-Year Convention | C25: 0.5 | D25: 0.5 | E25: 0.5 | F25: =CHOOSE(MATCH('02_Control'!$B$14,{"Downside","Base","Upside"},0),C25,D25,E25) -> 0.5 | G25: Uses mid-year discounting for projected cash flows.

Sheet 07_Forecast_IS
A1: Nexus Technologies — Forecast Income Statement
A2: ="Monthly detail + annual rollup | Scenario: "&'02_Control'!$B$14&" | Currency: "&'02_Control'!$B$12 -> Monthly detail + annual rollup | Scenario: Base | Currency: GBP
A4: Period | B4: ='05_Monthly_Model'!B4 -> 44927 | C4: ='05_Monthly_Model'!C4 -> 44958 | D4: ='05_Monthly_Model'!D4 -> 44986 | E4: ='05_Monthly_Model'!E4 -> 45017 | F4: ='05_Monthly_Model'!F4 -> 45047 | G4: ='05_Monthly_Model'!G4 -> 45078 | H4: ='05_Monthly_Model'!H4 -> 45108 | I4: ='05_Monthly_Model'!I4 -> 45139 | ... CG4: ='05_Monthly_Model'!CG4 -> 47453
A5: Period Type | B5: ='05_Monthly_Model'!B5 -> Actual | C5: ='05_Monthly_Model'!C5 -> Actual | D5: ='05_Monthly_Model'!D5 -> Actual | E5: ='05_Monthly_Model'!E5 -> Actual | F5: ='05_Monthly_Model'!F5 -> Actual | G5: ='05_Monthly_Model'!G5 -> Actual | H5: ='05_Monthly_Model'!H5 -> Actual | I5: ='05_Monthly_Model'!I5 -> Actual | ... CG5: ='05_Monthly_Model'!CG5 -> Forecast
A6: Calendar Year | B6: =YEAR(B4) -> 2023 | C6: =YEAR(C4) -> 2023 | D6: =YEAR(D4) -> 2023 | E6: =YEAR(E4) -> 2023 | F6: =YEAR(F4) -> 2023 | G6: =YEAR(G4) -> 2023 | H6: =YEAR(H4) -> 2023 | I6: =YEAR(I4) -> 2023 | ... CG6: =YEAR(CG4) -> 2029
A7: Quarter | B7: ="Q"&ROUNDUP(MONTH(B4)/3,0) -> Q1 | C7: ="Q"&ROUNDUP(MONTH(C4)/3,0) -> Q1 | D7: ="Q"&ROUNDUP(MONTH(D4)/3,0) -> Q1 | E7: ="Q"&ROUNDUP(MONTH(E4)/3,0) -> Q2 | F7: ="Q"&ROUNDUP(MONTH(F4)/3,0) -> Q2 | G7: ="Q"&ROUNDUP(MONTH(G4)/3,0) -> Q2 | H7: ="Q"&ROUNDUP(MONTH(H4)/3,0) -> Q3 | I7: ="Q"&ROUNDUP(MONTH(I4)/3,0) -> Q3 | ... CG7: ="Q"&ROUNDUP(MONTH(CG4)/3,0) -> Q4
A9: Revenue
A10: Recognised Revenue | B10: ='05_Monthly_Model'!B10 -> 1466626.4 | C10: ='05_Monthly_Model'!C10 -> 1641714.9 | D10: ='05_Monthly_Model'!D10 -> 1917718.6 | E10: ='05_Monthly_Model'!E10 -> 2122884.7 | F10: ='05_Monthly_Model'!F10 -> 2373771 | G10: ='05_Monthly_Model'!G10 -> 2624063.5 | H10: ='05_Monthly_Model'!H10 -> 2899362.8 | I10: ='05_Monthly_Model'!I10 -> 3163202.6 | ... CG10: ='05_Monthly_Model'!CG10 -> 8805014.1
A12: Operating Expenses
A13: Payroll Cost | B13: ='05_Monthly_Model'!B19 -> 4641129.1 | C13: ='05_Monthly_Model'!C19 -> 4731102.6 | D13: ='05_Monthly_Model'!D19 -> 4807431.4 | E13: ='05_Monthly_Model'!E19 -> 4868707.2 | F13: ='05_Monthly_Model'!F19 -> 4929130.6 | G13: ='05_Monthly_Model'!G19 -> 4974433.4 | H13: ='05_Monthly_Model'!H19 -> 5078537 | I13: ='05_Monthly_Model'!I19 -> 5101870.2 | ... CG13: ='05_Monthly_Model'!CG19 -> 11627538
A14: AP / Vendor Spend | B14: ='05_Monthly_Model'!B20 -> 291150.19 | C14: ='05_Monthly_Model'!C20 -> 658218.22 | D14: ='05_Monthly_Model'!D20 -> 560331.15 | E14: ='05_Monthly_Model'!E20 -> 755499.01 | F14: ='05_Monthly_Model'!F20 -> 519926.93 | G14: ='05_Monthly_Model'!G20 -> 679161.62 | H14: ='05_Monthly_Model'!H20 -> 588706.85 | I14: ='05_Monthly_Model'!I20 -> 863983.56 | ... CG14: ='05_Monthly_Model'!CG20 -> 108687.14
A15: Operating Expense Proxy | B15: ='05_Monthly_Model'!B21 -> 4932279.3 | C15: ='05_Monthly_Model'!C21 -> 5389320.9 | D15: ='05_Monthly_Model'!D21 -> 5367762.6 | E15: ='05_Monthly_Model'!E21 -> 5624206.2 | F15: ='05_Monthly_Model'!F21 -> 5449057.5 | G15: ='05_Monthly_Model'!G21 -> 5653595 | H15: ='05_Monthly_Model'!H21 -> 5667243.8 | I15: ='05_Monthly_Model'!I21 -> 5965853.7 | ... CG15: ='05_Monthly_Model'!CG21 -> 11736225
A16: Profitability
A17: Operating Profit | B17: ='05_Monthly_Model'!B23 -> -3465652.9 | C17: ='05_Monthly_Model'!C23 -> -3747605.9 | D17: ='05_Monthly_Model'!D23 -> -3450043.9 | E17: ='05_Monthly_Model'!E23 -> -3501321.5 | F17: ='05_Monthly_Model'!F23 -> -3075286.5 | G17: ='05_Monthly_Model'!G23 -> -3029531.5 | H17: ='05_Monthly_Model'!H23 -> -2767881 | I17: ='05_Monthly_Model'!I23 -> -2802651.1 | ... CG17: ='05_Monthly_Model'!CG23 -> -2931211.3
A18: Operating Margin | B18: ='05_Monthly_Model'!B25 -> -2.36301 | C18: ='05_Monthly_Model'!C25 -> -2.2827385 | D18: ='05_Monthly_Model'!D25 -> -1.7990355 | E18: ='05_Monthly_Model'!E25 -> -1.6493225 | F18: ='05_Monthly_Model'!F25 -> -1.2955279 | G18: ='05_Monthly_Model'!G25 -> -1.1545191 | H18: ='05_Monthly_Model'!H25 -> -0.95465151 | I18: ='05_Monthly_Model'!I25 -> -0.88601695 | ... CG18: ='05_Monthly_Model'!CG25 -> -0.33290251
A20: Efficiency Metrics
A21: Active FTE | B21: ='05_Monthly_Model'!B26 -> 452 | C21: ='05_Monthly_Model'!C26 -> 461 | D21: ='05_Monthly_Model'!D26 -> 476 | E21: ='05_Monthly_Model'!E26 -> 487 | F21: ='05_Monthly_Model'!F26 -> 496 | G21: ='05_Monthly_Model'!G26 -> 505 | H21: ='05_Monthly_Model'!H26 -> 513 | I21: ='05_Monthly_Model'!I26 -> 520 | ... CG21: ='05_Monthly_Model'!CG26 -> 1097.926
A22: Revenue per Active FTE | B22: ='05_Monthly_Model'!B27 -> 3244.7487 | C22: ='05_Monthly_Model'!C27 -> 3561.2038 | D22: ='05_Monthly_Model'!D27 -> 4028.8207 | E22: ='05_Monthly_Model'!E27 -> 4359.1062 | F22: ='05_Monthly_Model'!F27 -> 4785.8286 | G22: ='05_Monthly_Model'!G27 -> 5196.1654 | H22: ='05_Monthly_Model'!H27 -> 5651.7793 | I22: ='05_Monthly_Model'!I27 -> 6083.0819 | ... CG22: ='05_Monthly_Model'!CG27 -> 8019.6792
A24: Operating Expense Check | B24: =B15-(B13+B14) -> 0 | C24: =C15-(C13+C14) -> 0 | D24: =D15-(D13+D14) -> 0 | E24: =E15-(E13+E14) -> 0 | F24: =F15-(F13+F14) -> 0 | G24: =G15-(G13+G14) -> 0 | H24: =H15-(H13+H14) -> 0 | I24: =I15-(I13+I14) -> 0 | ... CG24: =CG15-(CG13+CG14) -> 0
A25: Operating Profit Check | B25: =B10-B15-B17 -> 0 | C25: =C10-C15-C17 -> 0 | D25: =D10-D15-D17 -> 0 | E25: =E10-E15-E17 -> 0 | F25: =F10-F15-F17 -> 0 | G25: =G10-G15-G17 -> 0 | H25: =H10-H15-H17 -> 0 | I25: =I10-I15-I17 -> 0 | ... CG25: =CG10-CG15-CG17 -> 0
A27: ANNUAL SUMMARY
B28: 2023 | C28: 2024 | D28: 2025 | E28: 2026 | F28: 2027 | G28: 2028 | H28: 2029
A29: Period Composition | B29: {=IF(SUMPRODUCT(('05_Monthly_Model'!$B$6:$CG$6=B$28)*($B$5:$CG$5="Forecast"))=0,"Actual",IF(SUMPRODUCT(('05_Monthly_Model'!$B$6:$CG$6=B$28)*($B$5:$CG$5="Actual"))=0,"Forecast","Blended"))} -> Actual | C29: {=IF(SUMPRODUCT(('05_Monthly_Model'!$B$6:$CG$6=C$28)*($B$5:$CG$5="Forecast"))=0,"Actual",IF(SUMPRODUCT(('05_Monthly_Model'!$B$6:$CG$6=C$28)*($B$5:$CG$5="Actual"))=0,"Forecast","Blended"))} -> Actual | D29: {=IF(SUMPRODUCT(('05_Monthly_Model'!$B$6:$CG$6=D$28)*($B$5:$CG$5="Forecast"))=0,"Actual",IF(SUMPRODUCT(('05_Monthly_Model'!$B$6:$CG$6=D$28)*($B$5:$CG$5="Actual"))=0,"Forecast","Blended"))} -> Actual | E29: 2026A/F | F29: {=IF(SUMPRODUCT(('05_Monthly_Model'!$B$6:$CG$6=F$28)*($B$5:$CG$5="Forecast"))=0,"Actual",IF(SUMPRODUCT(('05_Monthly_Model'!$B$6:$CG$6=F$28)*($B$5:$CG$5="Actual"))=0,"Forecast","Blended"))} -> Forecast | G29: {=IF(SUMPRODUCT(('05_Monthly_Model'!$B$6:$CG$6=G$28)*($B$5:$CG$5="Forecast"))=0,"Actual",IF(SUMPRODUCT(('05_Monthly_Model'!$B$6:$CG$6=G$28)*($B$5:$CG$5="Actual"))=0,"Forecast","Blended"))} -> Forecast | H29: {=IF(SUMPRODUCT(('05_Monthly_Model'!$B$6:$CG$6=H$28)*($B$5:$CG$5="Forecast"))=0,"Actual",IF(SUMPRODUCT(('05_Monthly_Model'!$B$6:$CG$6=H$28)*($B$5:$CG$5="Actual"))=0,"Forecast","Blended"))} -> Forecast
A30: Recognised Revenue | B30: =SUMIF('05_Monthly_Model'!$B$6:$CG$6,B$28,$B$10:$CG$10) -> 33098065 | C30: =SUMIF('05_Monthly_Model'!$B$6:$CG$6,C$28,$B$10:$CG$10) -> 55703643 | D30: =SUMIF('05_Monthly_Model'!$B$6:$CG$6,D$28,$B$10:$CG$10) -> 66187248 | E30: =SUMIF('05_Monthly_Model'!$B$6:$CG$6,E$28,$B$10:$CG$10) -> 70828413 | F30: =SUMIF('05_Monthly_Model'!$B$6:$CG$6,F$28,$B$10:$CG$10) -> 78829169 | G30: =SUMIF('05_Monthly_Model'!$B$6:$CG$6,G$28,$B$10:$CG$10) -> 88826681 | H30: =SUMIF('05_Monthly_Model'!$B$6:$CG$6,H$28,$B$10:$CG$10) -> 1.0009213e+08
A31: Payroll Cost | B31: =SUMIF('05_Monthly_Model'!$B$6:$CG$6,B$28,$B$13:$CG$13) -> 60322073 | C31: =SUMIF('05_Monthly_Model'!$B$6:$CG$6,C$28,$B$13:$CG$13) -> 71431930 | D31: =SUMIF('05_Monthly_Model'!$B$6:$CG$6,D$28,$B$13:$CG$13) -> 84152605 | E31: =SUMIF('05_Monthly_Model'!$B$6:$CG$6,E$28,$B$13:$CG$13) -> 93297269 | F31: =SUMIF('05_Monthly_Model'!$B$6:$CG$6,F$28,$B$13:$CG$13) -> 1.0409855e+08 | G31: =SUMIF('05_Monthly_Model'!$B$6:$CG$6,G$28,$B$13:$CG$13) -> 1.1730085e+08 | H31: =SUMIF('05_Monthly_Model'!$B$6:$CG$6,H$28,$B$13:$CG$13) -> 1.3217753e+08
A32: AP / Vendor Spend | B32: =SUMIF('05_Monthly_Model'!$B$6:$CG$6,B$28,$B$14:$CG$14) -> 6933102.1 | C32: =SUMIF('05_Monthly_Model'!$B$6:$CG$6,C$28,$B$14:$CG$14) -> 6854105.2 | D32: =SUMIF('05_Monthly_Model'!$B$6:$CG$6,D$28,$B$14:$CG$14) -> 7527033.5 | E32: =SUMIF('05_Monthly_Model'!$B$6:$CG$6,E$28,$B$14:$CG$14) -> 3858760.2 | F32: =SUMIF('05_Monthly_Model'!$B$6:$CG$6,F$28,$B$14:$CG$14) -> 1031425.9 | G32: =SUMIF('05_Monthly_Model'!$B$6:$CG$6,G$28,$B$14:$CG$14) -> 1134917.8 | H32: =SUMIF('05_Monthly_Model'!$B$6:$CG$6,H$28,$B$14:$CG$14) -> 1248793.9
A33: Operating Expense Proxy | B33: =SUMIF('05_Monthly_Model'!$B$6:$CG$6,B$28,$B$15:$CG$15) -> 67255175 | C33: =SUMIF('05_Monthly_Model'!$B$6:$CG$6,C$28,$B$15:$CG$15) -> 78286035 | D33: =SUMIF('05_Monthly_Model'!$B$6:$CG$6,D$28,$B$15:$CG$15) -> 91679639 | E33: =SUMIF('05_Monthly_Model'!$B$6:$CG$6,E$28,$B$15:$CG$15) -> 97156029 | F33: =SUMIF('05_Monthly_Model'!$B$6:$CG$6,F$28,$B$15:$CG$15) -> 1.0512997e+08 | G33: =SUMIF('05_Monthly_Model'!$B$6:$CG$6,G$28,$B$15:$CG$15) -> 1.1843577e+08 | H33: =SUMIF('05_Monthly_Model'!$B$6:$CG$6,H$28,$B$15:$CG$15) -> 1.3342633e+08
A34: Operating Profit | B34: =B30-B33 -> -34157110 | C34: =C30-C33 -> -22582392 | D34: =D30-D33 -> -25492390 | E34: =E30-E33 -> -26327616 | F34: =F30-F33 -> -26300805 | G34: =G30-G33 -> -29609086 | H34: =H30-H33 -> -33334200
A35: Operating Margin | B35: =IFERROR(B34/B30,"") -> -1.0319972 | C35: =IFERROR(C34/C30,"") -> -0.40540242 | D35: =IFERROR(D34/D30,"") -> -0.38515561 | E35: =IFERROR(E34/E30,"") -> -0.37170982 | F35: =IFERROR(F34/F30,"") -> -0.33364305 | G35: =IFERROR(G34/G30,"") -> -0.3333355 | H35: =IFERROR(H34/H30,"") -> -0.33303518
A36: Active FTE | B36: =INDEX($B$21:$CG$21,MATCH(DATE(B$28,12,1),$B$4:$CG$4,0)) -> 552 | C36: =INDEX($B$21:$CG$21,MATCH(DATE(C$28,12,1),$B$4:$CG$4,0)) -> 685 | D36: =INDEX($B$21:$CG$21,MATCH(DATE(D$28,12,1),$B$4:$CG$4,0)) -> 819 | E36: =INDEX($B$21:$CG$21,MATCH(DATE(E$28,12,1),$B$4:$CG$4,0)) -> 885.20887 | F36: =INDEX($B$21:$CG$21,MATCH(DATE(F$28,12,1),$B$4:$CG$4,0)) -> 951.0898 | G36: =INDEX($B$21:$CG$21,MATCH(DATE(G$28,12,1),$B$4:$CG$4,0)) -> 1021.8739 | H36: =INDEX($B$21:$CG$21,MATCH(DATE(H$28,12,1),$B$4:$CG$4,0)) -> 1097.926
A37: Revenue per Active FTE | B37: =IFERROR(B30/B36,"") -> 59960.262 | C37: =IFERROR(C30/C36,"") -> 81319.187 | D37: =IFERROR(D30/D36,"") -> 80814.711 | E37: =IFERROR(E30/E36,"") -> 80013.221 | F37: =IFERROR(F30/F36,"") -> 82882.993 | G37: =IFERROR(G30/G36,"") -> 86925.288 | H37: =IFERROR(H30/H36,"") -> 91164.732

Sheet 08_Forecast_BS
A1: Nexus Technologies — Forecast Balance Sheet Bridge
A2: ="Scenario: "&'02_Control'!$B$14&" | Currency: "&'02_Control'!$B$12&" | Units: £ actual" -> Scenario: Base | Currency: GBP | Units: £ actual
A4: Period | B4: ='05_Monthly_Model'!B4 -> 44927 | C4: ='05_Monthly_Model'!C4 -> 44958 | D4: ='05_Monthly_Model'!D4 -> 44986 | E4: ='05_Monthly_Model'!E4 -> 45017 | F4: ='05_Monthly_Model'!F4 -> 45047 | G4: ='05_Monthly_Model'!G4 -> 45078 | H4: ='05_Monthly_Model'!H4 -> 45108 | I4: ='05_Monthly_Model'!I4 -> 45139 | ... CG4: ='05_Monthly_Model'!CG4 -> 47453
A5: Period Type | B5: ='05_Monthly_Model'!B5 -> Actual | C5: ='05_Monthly_Model'!C5 -> Actual | D5: ='05_Monthly_Model'!D5 -> Actual | E5: ='05_Monthly_Model'!E5 -> Actual | F5: ='05_Monthly_Model'!F5 -> Actual | G5: ='05_Monthly_Model'!G5 -> Actual | H5: ='05_Monthly_Model'!H5 -> Actual | I5: ='05_Monthly_Model'!I5 -> Actual | ... CG5: ='05_Monthly_Model'!CG5 -> Forecast
A6: Calendar Year | B6: =YEAR(B4) -> 2023 | C6: =YEAR(C4) -> 2023 | D6: =YEAR(D4) -> 2023 | E6: =YEAR(E4) -> 2023 | F6: =YEAR(F4) -> 2023 | G6: =YEAR(G4) -> 2023 | H6: =YEAR(H4) -> 2023 | I6: =YEAR(I4) -> 2023 | ... CG6: =YEAR(CG4) -> 2029
A7: Quarter | B7: ="Q"&ROUNDUP(MONTH(B4)/3,0) -> Q1 | C7: ="Q"&ROUNDUP(MONTH(C4)/3,0) -> Q1 | D7: ="Q"&ROUNDUP(MONTH(D4)/3,0) -> Q1 | E7: ="Q"&ROUNDUP(MONTH(E4)/3,0) -> Q2 | F7: ="Q"&ROUNDUP(MONTH(F4)/3,0) -> Q2 | G7: ="Q"&ROUNDUP(MONTH(G4)/3,0) -> Q2 | H7: ="Q"&ROUNDUP(MONTH(H4)/3,0) -> Q3 | I7: ="Q"&ROUNDUP(MONTH(I4)/3,0) -> Q3 | ... CG7: ="Q"&ROUNDUP(MONTH(CG4)/3,0) -> Q4
A9: Working Capital Assets
A10: Accounts Receivable / Open AR Exposure | B10: ='05_Monthly_Model'!B31 -> 1073080.8 | C10: ='05_Monthly_Model'!C31 -> 584121.35 | D10: ='05_Monthly_Model'!D31 -> 740587.59 | E10: ='05_Monthly_Model'!E31 -> 720385.8 | F10: ='05_Monthly_Model'!F31 -> 848665.75 | G10: ='05_Monthly_Model'!G31 -> 917567.49 | H10: ='05_Monthly_Model'!H31 -> 557672.58 | I10: ='05_Monthly_Model'!I31 -> 648072.02 | ... CG10: ='05_Monthly_Model'!CG31 -> 1263780.8
A12: Working Capital Liabilities
A13: Accounts Payable / Open AP Liability | B13: ='05_Monthly_Model'!B32 -> 0 | C13: ='05_Monthly_Model'!C32 -> 0 | D13: ='05_Monthly_Model'!D32 -> 0 | E13: ='05_Monthly_Model'!E32 -> 0 | F13: ='05_Monthly_Model'!F32 -> 0 | G13: ='05_Monthly_Model'!G32 -> 0 | H13: ='05_Monthly_Model'!H32 -> 0 | I13: ='05_Monthly_Model'!I32 -> 0 | ... CG13: ='05_Monthly_Model'!CG32 -> 13042.457
A14: Deferred Revenue | B14: ='05_Monthly_Model'!B33 -> 2788373.4 | C14: ='05_Monthly_Model'!C33 -> 4663315.8 | D14: ='05_Monthly_Model'!D33 -> 6214122.3 | E14: ='05_Monthly_Model'!E33 -> 7963201 | F14: ='05_Monthly_Model'!F33 -> 9081122.6 | G14: ='05_Monthly_Model'!G33 -> 10830418 | H14: ='05_Monthly_Model'!H33 -> 11719083 | I14: ='05_Monthly_Model'!I33 -> 12743268 | ... CG14: ='05_Monthly_Model'!CG33 -> 6740164.1
A16: Net Working Capital
A17: Net Working Capital | B17: =B10-B13-B14 -> -1715292.6 | C17: =C10-C13-C14 -> -4079194.4 | D17: =D10-D13-D14 -> -5473534.7 | E17: =E10-E13-E14 -> -7242815.2 | F17: =F10-F13-F14 -> -8232456.9 | G17: =G10-G13-G14 -> -9912850.9 | H17: =H10-H13-H14 -> -11161411 | I17: =I10-I13-I14 -> -12095196 | ... CG17: =CG10-CG13-CG14 -> -5489425.8
A19: Cash Bridge
A20: Opening Cash / Net Cash | B20: =_xlfn.XLOOKUP("Opening Cash Balance",tbl_assumptions[Driver],tbl_assumptions[Selected Scenario])/'02_Control'!$B$18 -> 10000000 | C20: =B26 -> 9127080.9 | D20: =C26 -> 7563454.4 | E20: =D26 -> 5121606.4 | F20: =E26 -> 3419984.1 | G20: =F26 -> 849127.75 | H20: =G26 -> -642524.07 | I20: =H26 -> -2675538.4 | J20: =I26 -> -4370086.6 | ... CG20: =CF26 -> -2.4128417e+08
A21: Operating Profit | B21: ='05_Monthly_Model'!B23 -> -3465652.9 | C21: ='05_Monthly_Model'!C23 -> -3747605.9 | D21: ='05_Monthly_Model'!D23 -> -3450043.9 | E21: ='05_Monthly_Model'!E23 -> -3501321.5 | F21: ='05_Monthly_Model'!F23 -> -3075286.5 | G21: ='05_Monthly_Model'!G23 -> -3029531.5 | H21: ='05_Monthly_Model'!H23 -> -2767881 | I21: ='05_Monthly_Model'!I23 -> -2802651.1 | ... CG21: ='05_Monthly_Model'!CG23 -> -2931211.3
A22: Cash Collected | B22: ='05_Monthly_Model'!B30 -> 3771182.3 | C22: ='05_Monthly_Model'!C30 -> 3312454.7 | D22: ='05_Monthly_Model'!D30 -> 3172057.9 | E22: ='05_Monthly_Model'!E30 -> 3613516.5 | F22: ='05_Monthly_Model'!F30 -> 3000694 | G22: ='05_Monthly_Model'!G30 -> 3983097.2 | H22: ='05_Monthly_Model'!H30 -> 3687227.4 | I22: ='05_Monthly_Model'!I30 -> 4042353.8 | ... CG22: ='05_Monthly_Model'!CG30 -> 6908668.2
A23: Supplier Cash Paid | B23: ='05_Monthly_Model'!B34 -> 2972.29 | C23: ='05_Monthly_Model'!C34 -> 144978.52 | D23: ='05_Monthly_Model'!D34 -> 806474.41 | E23: ='05_Monthly_Model'!E34 -> 446431.7 | F23: ='05_Monthly_Model'!F34 -> 642419.77 | G23: ='05_Monthly_Model'!G34 -> 500315.7 | H23: ='05_Monthly_Model'!H34 -> 641704.78 | I23: ='05_Monthly_Model'!I34 -> 635031.87 | ... CG23: ='05_Monthly_Model'!CG34 -> 92384.073
A24: Payroll Cash Paid | B24: ='05_Monthly_Model'!B19 -> 4641129.1 | C24: ='05_Monthly_Model'!C19 -> 4731102.6 | D24: ='05_Monthly_Model'!D19 -> 4807431.4 | E24: ='05_Monthly_Model'!E19 -> 4868707.2 | F24: ='05_Monthly_Model'!F19 -> 4929130.6 | G24: ='05_Monthly_Model'!G19 -> 4974433.4 | H24: ='05_Monthly_Model'!H19 -> 5078537 | I24: ='05_Monthly_Model'!I19 -> 5101870.2 | ... CG24: ='05_Monthly_Model'!CG19 -> 11627538
A25: Net Operating Cash Movement | B25: =B22-B23-B24 -> -872919.13 | C25: =C22-C23-C24 -> -1563626.5 | D25: =D22-D23-D24 -> -2441848 | E25: =E22-E23-E24 -> -1701622.4 | F25: =F22-F23-F24 -> -2570856.3 | G25: =G22-G23-G24 -> -1491651.8 | H25: =H22-H23-H24 -> -2033014.3 | I25: =I22-I23-I24 -> -1694548.2 | ... CG25: =CG22-CG23-CG24 -> -4811254.2
A26: Closing Cash / Net Cash | B26: =B20+B25 -> 9127080.9 | C26: =C20+C25 -> 7563454.4 | D26: =D20+D25 -> 5121606.4 | E26: =E20+E25 -> 3419984.1 | F26: =F20+F25 -> 849127.75 | G26: =G20+G25 -> -642524.07 | H26: =H20+H25 -> -2675538.4 | I26: =I20+I25 -> -4370086.6 | ... CG26: =CG20+CG25 -> -2.4609542e+08
A28: Checks
A29: Cash Rollforward Check | B29: =B20+B25-B26 -> 0 | C29: =C20+C25-C26 -> 0 | D29: =D20+D25-D26 -> 0 | E29: =E20+E25-E26 -> 0 | F29: =F20+F25-F26 -> 0 | G29: =G20+G25-G26 -> 0 | H29: =H20+H25-H26 -> 0 | I29: =I20+I25-I26 -> 0 | ... CG29: =CG20+CG25-CG26 -> 0
A31: Annual Balance Sheet Bridge Summary
B32: 2023 | C32: 2024 | D32: 2025 | E32: 2026 | F32: 2027 | G32: 2028 | H32: 2029
A33: Period Composition | B33: {=IF(SUMPRODUCT(('05_Monthly_Model'!$B$6:$CG$6=B$32)*($B$5:$CG$5="Forecast"))=0,"Actual",IF(SUMPRODUCT(('05_Monthly_Model'!$B$6:$CG$6=B$32)*($B$5:$CG$5="Actual"))=0,"Forecast","Blended"))} -> Actual | C33: {=IF(SUMPRODUCT(('05_Monthly_Model'!$B$6:$CG$6=C$32)*($B$5:$CG$5="Forecast"))=0,"Actual",IF(SUMPRODUCT(('05_Monthly_Model'!$B$6:$CG$6=C$32)*($B$5:$CG$5="Actual"))=0,"Forecast","Blended"))} -> Actual | D33: {=IF(SUMPRODUCT(('05_Monthly_Model'!$B$6:$CG$6=D$32)*($B$5:$CG$5="Forecast"))=0,"Actual",IF(SUMPRODUCT(('05_Monthly_Model'!$B$6:$CG$6=D$32)*($B$5:$CG$5="Actual"))=0,"Forecast","Blended"))} -> Actual | E33: 2026A/F | F33: {=IF(SUMPRODUCT(('05_Monthly_Model'!$B$6:$CG$6=F$32)*($B$5:$CG$5="Forecast"))=0,"Actual",IF(SUMPRODUCT(('05_Monthly_Model'!$B$6:$CG$6=F$32)*($B$5:$CG$5="Actual"))=0,"Forecast","Blended"))} -> Forecast | G33: {=IF(SUMPRODUCT(('05_Monthly_Model'!$B$6:$CG$6=G$32)*($B$5:$CG$5="Forecast"))=0,"Actual",IF(SUMPRODUCT(('05_Monthly_Model'!$B$6:$CG$6=G$32)*($B$5:$CG$5="Actual"))=0,"Forecast","Blended"))} -> Forecast | H33: {=IF(SUMPRODUCT(('05_Monthly_Model'!$B$6:$CG$6=H$32)*($B$5:$CG$5="Forecast"))=0,"Actual",IF(SUMPRODUCT(('05_Monthly_Model'!$B$6:$CG$6=H$32)*($B$5:$CG$5="Actual"))=0,"Forecast","Blended"))} -> Forecast
A34: Working Capital Assets
A35: Accounts Receivable / Open AR Exposure | B35: =_xlfn.XLOOKUP(DATE(B$32,12,1),$B$4:$CG$4,$B$10:$CG$10) -> 933546.37 | C35: =_xlfn.XLOOKUP(DATE(C$32,12,1),$B$4:$CG$4,$B$10:$CG$10) -> 925259.56 | D35: =_xlfn.XLOOKUP(DATE(D$32,12,1),$B$4:$CG$4,$B$10:$CG$10) -> 1086816.3 | E35: =_xlfn.XLOOKUP(DATE(E$32,12,1),$B$4:$CG$4,$B$10:$CG$10) -> 948620.67 | F35: =_xlfn.XLOOKUP(DATE(F$32,12,1),$B$4:$CG$4,$B$10:$CG$10) -> 1043804 | G35: =_xlfn.XLOOKUP(DATE(G$32,12,1),$B$4:$CG$4,$B$10:$CG$10) -> 1148538 | H35: =_xlfn.XLOOKUP(DATE(H$32,12,1),$B$4:$CG$4,$B$10:$CG$10) -> 1263780.8
A37: Working Capital Liabilities
A38: Accounts Payable / Open AP Liability | B38: =_xlfn.XLOOKUP(DATE(B$32,12,1),$B$4:$CG$4,$B$13:$CG$13) -> 0 | C38: =_xlfn.XLOOKUP(DATE(C$32,12,1),$B$4:$CG$4,$B$13:$CG$13) -> 0 | D38: =_xlfn.XLOOKUP(DATE(D$32,12,1),$B$4:$CG$4,$B$13:$CG$13) -> 0 | E38: =_xlfn.XLOOKUP(DATE(E$32,12,1),$B$4:$CG$4,$B$13:$CG$13) -> 9789.9454 | F38: =_xlfn.XLOOKUP(DATE(F$32,12,1),$B$4:$CG$4,$B$13:$CG$13) -> 10772.256 | G38: =_xlfn.XLOOKUP(DATE(G$32,12,1),$B$4:$CG$4,$B$13:$CG$13) -> 11853.13 | H38: =_xlfn.XLOOKUP(DATE(H$32,12,1),$B$4:$CG$4,$B$13:$CG$13) -> 13042.457
A39: Deferred Revenue | B39: =_xlfn.XLOOKUP(DATE(B$32,12,1),$B$4:$CG$4,$B$14:$CG$14) -> 13878237 | C39: =_xlfn.XLOOKUP(DATE(C$32,12,1),$B$4:$CG$4,$B$14:$CG$14) -> 17914006 | D39: =_xlfn.XLOOKUP(DATE(D$32,12,1),$B$4:$CG$4,$B$14:$CG$14) -> 20964419 | E39: =_xlfn.XLOOKUP(DATE(E$32,12,1),$B$4:$CG$4,$B$14:$CG$14) -> 5059310.3 | F39: =_xlfn.XLOOKUP(DATE(F$32,12,1),$B$4:$CG$4,$B$14:$CG$14) -> 5566954.8 | G39: =_xlfn.XLOOKUP(DATE(G$32,12,1),$B$4:$CG$4,$B$14:$CG$14) -> 6125535.8 | H39: =_xlfn.XLOOKUP(DATE(H$32,12,1),$B$4:$CG$4,$B$14:$CG$14) -> 6740164.1
A41: Net Working Capital
A42: Net Working Capital | B42: =B35-B38-B39 -> -12944691 | C42: =C35-C38-C39 -> -16988747 | D42: =D35-D38-D39 -> -19877602 | E42: =E35-E38-E39 -> -4120479.5 | F42: =F35-F38-F39 -> -4533923.1 | G42: =G35-G38-G39 -> -4988851 | H42: =H35-H38-H39 -> -5489425.8
A44: Cash Bridge
A45: Opening Cash / Net Cash | B45: =_xlfn.XLOOKUP(DATE(B$32,1,1),$B$4:$CG$4,$B$20:$CG$20) -> 10000000 | C45: =_xlfn.XLOOKUP(DATE(C$32,1,1),$B$4:$CG$4,$B$20:$CG$20) -> -12902996 | D45: =_xlfn.XLOOKUP(DATE(D$32,1,1),$B$4:$CG$4,$B$20:$CG$20) -> -35484382 | E45: =_xlfn.XLOOKUP(DATE(E$32,1,1),$B$4:$CG$4,$B$20:$CG$20) -> -62905551 | F45: =_xlfn.XLOOKUP(DATE(F$32,1,1),$B$4:$CG$4,$B$20:$CG$20) -> -1.066979e+08 | G45: =_xlfn.XLOOKUP(DATE(G$32,1,1),$B$4:$CG$4,$B$20:$CG$20) -> -1.4611086e+08 | H45: =_xlfn.XLOOKUP(DATE(H$32,1,1),$B$4:$CG$4,$B$20:$CG$20) -> -1.9223566e+08
A46: Cash Collected | B46: =SUMIFS($B$22:$CG$22,$B$4:$CG$4,">="&DATE(B$32,1,1),$B$4:$CG$4,"<="&DATE(B$32,12,1)) -> 43455105 | C46: =SUMIFS($B$22:$CG$22,$B$4:$CG$4,">="&DATE(C$32,1,1),$B$4:$CG$4,"<="&DATE(C$32,12,1)) -> 54639238 | D46: =SUMIFS($B$22:$CG$22,$B$4:$CG$4,">="&DATE(D$32,1,1),$B$4:$CG$4,"<="&DATE(D$32,12,1)) -> 63485823 | E46: =SUMIFS($B$22:$CG$22,$B$4:$CG$4,">="&DATE(E$32,1,1),$B$4:$CG$4,"<="&DATE(E$32,12,1)) -> 53379766 | F46: =SUMIFS($B$22:$CG$22,$B$4:$CG$4,">="&DATE(F$32,1,1),$B$4:$CG$4,"<="&DATE(F$32,12,1)) -> 65562298 | G46: =SUMIFS($B$22:$CG$22,$B$4:$CG$4,">="&DATE(G$32,1,1),$B$4:$CG$4,"<="&DATE(G$32,12,1)) -> 72140733 | H46: =SUMIFS($B$22:$CG$22,$B$4:$CG$4,">="&DATE(H$32,1,1),$B$4:$CG$4,"<="&DATE(H$32,12,1)) -> 79379240
A47: Supplier Cash Paid | B47: =SUMIFS($B$23:$CG$23,$B$4:$CG$4,">="&DATE(B$32,1,1),$B$4:$CG$4,"<="&DATE(B$32,12,1)) -> 6036027.5 | C47: =SUMIFS($B$23:$CG$23,$B$4:$CG$4,">="&DATE(C$32,1,1),$B$4:$CG$4,"<="&DATE(C$32,12,1)) -> 5788695.1 | D47: =SUMIFS($B$23:$CG$23,$B$4:$CG$4,">="&DATE(D$32,1,1),$B$4:$CG$4,"<="&DATE(D$32,12,1)) -> 6754386.5 | E47: =SUMIFS($B$23:$CG$23,$B$4:$CG$4,">="&DATE(E$32,1,1),$B$4:$CG$4,"<="&DATE(E$32,12,1)) -> 3874844.8 | F47: =SUMIFS($B$23:$CG$23,$B$4:$CG$4,">="&DATE(F$32,1,1),$B$4:$CG$4,"<="&DATE(F$32,12,1)) -> 876711.97 | G47: =SUMIFS($B$23:$CG$23,$B$4:$CG$4,">="&DATE(G$32,1,1),$B$4:$CG$4,"<="&DATE(G$32,12,1)) -> 964680.11 | H47: =SUMIFS($B$23:$CG$23,$B$4:$CG$4,">="&DATE(H$32,1,1),$B$4:$CG$4,"<="&DATE(H$32,12,1)) -> 1061474.8
A48: Payroll Cash Paid | B48: =SUMIFS($B$24:$CG$24,$B$4:$CG$4,">="&DATE(B$32,1,1),$B$4:$CG$4,"<="&DATE(B$32,12,1)) -> 60322073 | C48: =SUMIFS($B$24:$CG$24,$B$4:$CG$4,">="&DATE(C$32,1,1),$B$4:$CG$4,"<="&DATE(C$32,12,1)) -> 71431930 | D48: =SUMIFS($B$24:$CG$24,$B$4:$CG$4,">="&DATE(D$32,1,1),$B$4:$CG$4,"<="&DATE(D$32,12,1)) -> 84152605 | E48: =SUMIFS($B$24:$CG$24,$B$4:$CG$4,">="&DATE(E$32,1,1),$B$4:$CG$4,"<="&DATE(E$32,12,1)) -> 93297269 | F48: =SUMIFS($B$24:$CG$24,$B$4:$CG$4,">="&DATE(F$32,1,1),$B$4:$CG$4,"<="&DATE(F$32,12,1)) -> 1.0409855e+08 | G48: =SUMIFS($B$24:$CG$24,$B$4:$CG$4,">="&DATE(G$32,1,1),$B$4:$CG$4,"<="&DATE(G$32,12,1)) -> 1.1730085e+08 | H48: =SUMIFS($B$24:$CG$24,$B$4:$CG$4,">="&DATE(H$32,1,1),$B$4:$CG$4,"<="&DATE(H$32,12,1)) -> 1.3217753e+08
A49: Net Operating Cash Movement | B49: =B46-B47-B48 -> -22902996 | C49: =C46-C47-C48 -> -22581387 | D49: =D46-D47-D48 -> -27421169 | E49: =E46-E47-E48 -> -43792348 | F49: =F46-F47-F48 -> -39412962 | G49: =G46-G47-G48 -> -46124796 | H49: =H46-H47-H48 -> -53859767
A50: Closing Cash / Net Cash | B50: =_xlfn.XLOOKUP(DATE(B$32,12,1),$B$4:$CG$4,$B$26:$CG$26) -> -12902996 | C50: =_xlfn.XLOOKUP(DATE(C$32,12,1),$B$4:$CG$4,$B$26:$CG$26) -> -35484382 | D50: =_xlfn.XLOOKUP(DATE(D$32,12,1),$B$4:$CG$4,$B$26:$CG$26) -> -62905551 | E50: =_xlfn.XLOOKUP(DATE(E$32,12,1),$B$4:$CG$4,$B$26:$CG$26) -> -1.066979e+08 | F50: =_xlfn.XLOOKUP(DATE(F$32,12,1),$B$4:$CG$4,$B$26:$CG$26) -> -1.4611086e+08 | G50: =_xlfn.XLOOKUP(DATE(G$32,12,1),$B$4:$CG$4,$B$26:$CG$26) -> -1.9223566e+08 | H50: =_xlfn.XLOOKUP(DATE(H$32,12,1),$B$4:$CG$4,$B$26:$CG$26) -> -2.4609542e+08
A52: Checks
A53: Cash Rollforward Check | B53: =B45+B49-B50 -> 0 | C53: =C45+C49-C50 -> 0 | D53: =D45+D49-D50 -> 0 | E53: =E45+E49-E50 -> 0 | F53: =F45+F49-F50 -> 0 | G53: =G45+G49-G50 -> 0 | H53: =H45+H49-H50 -> 0
A54: Cash Continuity Check | B54: =0 -> 0 | C54: =C45-B50 -> 0 | D54: =D45-C50 -> 0 | E54: =E45-D50 -> 0 | F54: =F45-E50 -> 0 | G54: =G45-F50 -> 0 | H54: =H45-G50 -> 0

Sheet 09_Forecast_CFS
A1: Nexus Technologies — Forecast Cash Flow Statement
A2: ="Scenario: "&'02_Control'!$B$14&" | Currency: "&'02_Control'!$B$12&" | Units: £ actual" -> Scenario: Base | Currency: GBP | Units: £ actual
A3: This tab presents an operating cash flow proxy based on Atlas cash collection, supplier payment, and payroll cost data. It is not a full statutory cash flow statement until tax, capex, debt, interest, equity, and other financing/investing schedules are added.
A5: Period | B5: ='05_Monthly_Model'!B4 -> 44927 | C5: ='05_Monthly_Model'!C4 -> 44958 | D5: ='05_Monthly_Model'!D4 -> 44986 | E5: ='05_Monthly_Model'!E4 -> 45017 | F5: ='05_Monthly_Model'!F4 -> 45047 | G5: ='05_Monthly_Model'!G4 -> 45078 | H5: ='05_Monthly_Model'!H4 -> 45108 | I5: ='05_Monthly_Model'!I4 -> 45139 | ... CG5: ='05_Monthly_Model'!CG4 -> 47453
A6: Period Type | B6: ='05_Monthly_Model'!B5 -> Actual | C6: ='05_Monthly_Model'!C5 -> Actual | D6: ='05_Monthly_Model'!D5 -> Actual | E6: ='05_Monthly_Model'!E5 -> Actual | F6: ='05_Monthly_Model'!F5 -> Actual | G6: ='05_Monthly_Model'!G5 -> Actual | H6: ='05_Monthly_Model'!H5 -> Actual | I6: ='05_Monthly_Model'!I5 -> Actual | ... CG6: ='05_Monthly_Model'!CG5 -> Forecast
A7: Calendar Year | B7: =YEAR(B5) -> 2023 | C7: =YEAR(C5) -> 2023 | D7: =YEAR(D5) -> 2023 | E7: =YEAR(E5) -> 2023 | F7: =YEAR(F5) -> 2023 | G7: =YEAR(G5) -> 2023 | H7: =YEAR(H5) -> 2023 | I7: =YEAR(I5) -> 2023 | ... CG7: =YEAR(CG5) -> 2029
A8: Quarter | B8: ="Q"&ROUNDUP(MONTH(B5)/3,0) -> Q1 | C8: ="Q"&ROUNDUP(MONTH(C5)/3,0) -> Q1 | D8: ="Q"&ROUNDUP(MONTH(D5)/3,0) -> Q1 | E8: ="Q"&ROUNDUP(MONTH(E5)/3,0) -> Q2 | F8: ="Q"&ROUNDUP(MONTH(F5)/3,0) -> Q2 | G8: ="Q"&ROUNDUP(MONTH(G5)/3,0) -> Q2 | H8: ="Q"&ROUNDUP(MONTH(H5)/3,0) -> Q3 | I8: ="Q"&ROUNDUP(MONTH(I5)/3,0) -> Q3 | ... CG8: ="Q"&ROUNDUP(MONTH(CG5)/3,0) -> Q4
A10: Operating Cash Flow
A11: Cash Collected from Customers | B11: ='08_Forecast_BS'!B22 -> 3771182.3 | C11: ='08_Forecast_BS'!C22 -> 3312454.7 | D11: ='08_Forecast_BS'!D22 -> 3172057.9 | E11: ='08_Forecast_BS'!E22 -> 3613516.5 | F11: ='08_Forecast_BS'!F22 -> 3000694 | G11: ='08_Forecast_BS'!G22 -> 3983097.2 | H11: ='08_Forecast_BS'!H22 -> 3687227.4 | I11: ='08_Forecast_BS'!I22 -> 4042353.8 | ... CG11: ='08_Forecast_BS'!CG22 -> 6908668.2
A12: Supplier Cash Paid | B12: ='08_Forecast_BS'!B23 -> 2972.29 | C12: ='08_Forecast_BS'!C23 -> 144978.52 | D12: ='08_Forecast_BS'!D23 -> 806474.41 | E12: ='08_Forecast_BS'!E23 -> 446431.7 | F12: ='08_Forecast_BS'!F23 -> 642419.77 | G12: ='08_Forecast_BS'!G23 -> 500315.7 | H12: ='08_Forecast_BS'!H23 -> 641704.78 | I12: ='08_Forecast_BS'!I23 -> 635031.87 | ... CG12: ='08_Forecast_BS'!CG23 -> 92384.073
A13: Payroll Cash Paid | B13: ='08_Forecast_BS'!B24 -> 4641129.1 | C13: ='08_Forecast_BS'!C24 -> 4731102.6 | D13: ='08_Forecast_BS'!D24 -> 4807431.4 | E13: ='08_Forecast_BS'!E24 -> 4868707.2 | F13: ='08_Forecast_BS'!F24 -> 4929130.6 | G13: ='08_Forecast_BS'!G24 -> 4974433.4 | H13: ='08_Forecast_BS'!H24 -> 5078537 | I13: ='08_Forecast_BS'!I24 -> 5101870.2 | ... CG13: ='08_Forecast_BS'!CG24 -> 11627538
A14: Net Operating Cash Flow Proxy | B14: =B11-B12-B13 -> -872919.13 | C14: =C11-C12-C13 -> -1563626.5 | D14: =D11-D12-D13 -> -2441848 | E14: =E11-E12-E13 -> -1701622.4 | F14: =F11-F12-F13 -> -2570856.3 | G14: =G11-G12-G13 -> -1491651.8 | H14: =H11-H12-H13 -> -2033014.3 | I14: =I11-I12-I13 -> -1694548.2 | ... CG14: =CG11-CG12-CG13 -> -4811254.2
A16: Cash Bridge
A17: Opening Cash / Net Cash | B17: ='08_Forecast_BS'!B20 -> 10000000 | C17: ='08_Forecast_BS'!C20 -> 9127080.9 | D17: ='08_Forecast_BS'!D20 -> 7563454.4 | E17: ='08_Forecast_BS'!E20 -> 5121606.4 | F17: ='08_Forecast_BS'!F20 -> 3419984.1 | G17: ='08_Forecast_BS'!G20 -> 849127.75 | H17: ='08_Forecast_BS'!H20 -> -642524.07 | I17: ='08_Forecast_BS'!I20 -> -2675538.4 | ... CG17: ='08_Forecast_BS'!CG20 -> -2.4128417e+08
A18: Net Operating Cash Flow Proxy | B18: =B14 -> -872919.13 | C18: =C14 -> -1563626.5 | D18: =D14 -> -2441848 | E18: =E14 -> -1701622.4 | F18: =F14 -> -2570856.3 | G18: =G14 -> -1491651.8 | H18: =H14 -> -2033014.3 | I18: =I14 -> -1694548.2 | ... CG18: =CG14 -> -4811254.2
A19: Closing Cash / Net Cash | B19: ='08_Forecast_BS'!B26 -> 9127080.9 | C19: ='08_Forecast_BS'!C26 -> 7563454.4 | D19: ='08_Forecast_BS'!D26 -> 5121606.4 | E19: ='08_Forecast_BS'!E26 -> 3419984.1 | F19: ='08_Forecast_BS'!F26 -> 849127.75 | G19: ='08_Forecast_BS'!G26 -> -642524.07 | H19: ='08_Forecast_BS'!H26 -> -2675538.4 | I19: ='08_Forecast_BS'!I26 -> -4370086.6 | ... CG19: ='08_Forecast_BS'!CG26 -> -2.4609542e+08
A21: Checks
A22: Cash Movement Check | B22: =B17+B18-B19 -> 0 | C22: =C17+C18-C19 -> 0 | D22: =D17+D18-D19 -> 0 | E22: =E17+E18-E19 -> 0 | F22: =F17+F18-F19 -> 0 | G22: =G17+G18-G19 -> 0 | H22: =H17+H18-H19 -> 0 | I22: =I17+I18-I19 -> 0 | ... CG22: =CG17+CG18-CG19 -> 0
A23: Cash Continuity Check | B23: 0 | C23: =C17-B19 -> 0 | D23: =D17-C19 -> 0 | E23: =E17-D19 -> 0 | F23: =F17-E19 -> 0 | G23: =G17-F19 -> 0 | H23: =H17-G19 -> 0 | I23: =I17-H19 -> 0 | J23: =J17-I19 -> 0 | ... CG23: =CG17-CF19 -> 0
A25: Annual Summary
B26: 2023 | C26: 2024 | D26: 2025 | E26: 2026 | F26: 2027 | G26: 2028 | H26: 2029
A27: Period Composition | B27: {=IF(SUMPRODUCT(('05_Monthly_Model'!$B$6:$CG$6=B$26)*($B$5:$CG$5="Forecast"))=0,"Actual",IF(SUMPRODUCT(('05_Monthly_Model'!$B$6:$CG$6=B$26)*($B$5:$CG$5="Actual"))=0,"Forecast","Blended"))} -> Actual | C27: {=IF(SUMPRODUCT(('05_Monthly_Model'!$B$6:$CG$6=C$26)*($B$5:$CG$5="Forecast"))=0,"Actual",IF(SUMPRODUCT(('05_Monthly_Model'!$B$6:$CG$6=C$26)*($B$5:$CG$5="Actual"))=0,"Forecast","Blended"))} -> Actual | D27: {=IF(SUMPRODUCT(('05_Monthly_Model'!$B$6:$CG$6=D$26)*($B$5:$CG$5="Forecast"))=0,"Actual",IF(SUMPRODUCT(('05_Monthly_Model'!$B$6:$CG$6=D$26)*($B$5:$CG$5="Actual"))=0,"Forecast","Blended"))} -> Actual | E27: {=IF(SUMPRODUCT(('05_Monthly_Model'!$B$6:$CG$6=E$26)*($B$5:$CG$5="Forecast"))=0,"Actual",IF(SUMPRODUCT(('05_Monthly_Model'!$B$6:$CG$6=E$26)*($B$5:$CG$5="Actual"))=0,"Forecast","Blended"))} -> Actual | F27: {=IF(SUMPRODUCT(('05_Monthly_Model'!$B$6:$CG$6=F$26)*($B$5:$CG$5="Forecast"))=0,"Actual",IF(SUMPRODUCT(('05_Monthly_Model'!$B$6:$CG$6=F$26)*($B$5:$CG$5="Actual"))=0,"Forecast","Blended"))} -> Actual | G27: {=IF(SUMPRODUCT(('05_Monthly_Model'!$B$6:$CG$6=G$26)*($B$5:$CG$5="Forecast"))=0,"Actual",IF(SUMPRODUCT(('05_Monthly_Model'!$B$6:$CG$6=G$26)*($B$5:$CG$5="Actual"))=0,"Forecast","Blended"))} -> Actual | H27: {=IF(SUMPRODUCT(('05_Monthly_Model'!$B$6:$CG$6=H$26)*($B$5:$CG$5="Forecast"))=0,"Actual",IF(SUMPRODUCT(('05_Monthly_Model'!$B$6:$CG$6=H$26)*($B$5:$CG$5="Actual"))=0,"Forecast","Blended"))} -> Actual
A28: Operating Cash Flow
A29: Cash Collected from Customers | B29: =SUMIFS($B$11:$CG$11,$B$5:$CG$5,">="&DATE(B$26,1,1),$B$5:$CG$5,"<="&DATE(B$26,12,1)) -> 43455105 | C29: =SUMIFS($B$11:$CG$11,$B$5:$CG$5,">="&DATE(C$26,1,1),$B$5:$CG$5,"<="&DATE(C$26,12,1)) -> 54639238 | D29: =SUMIFS($B$11:$CG$11,$B$5:$CG$5,">="&DATE(D$26,1,1),$B$5:$CG$5,"<="&DATE(D$26,12,1)) -> 63485823 | E29: =SUMIFS($B$11:$CG$11,$B$5:$CG$5,">="&DATE(E$26,1,1),$B$5:$CG$5,"<="&DATE(E$26,12,1)) -> 53379766 | F29: =SUMIFS($B$11:$CG$11,$B$5:$CG$5,">="&DATE(F$26,1,1),$B$5:$CG$5,"<="&DATE(F$26,12,1)) -> 65562298 | G29: =SUMIFS($B$11:$CG$11,$B$5:$CG$5,">="&DATE(G$26,1,1),$B$5:$CG$5,"<="&DATE(G$26,12,1)) -> 72140733 | H29: =SUMIFS($B$11:$CG$11,$B$5:$CG$5,">="&DATE(H$26,1,1),$B$5:$CG$5,"<="&DATE(H$26,12,1)) -> 79379240
A30: Supplier Cash Paid | B30: =SUMIFS($B$12:$CG$12,$B$5:$CG$5,">="&DATE(B$26,1,1),$B$5:$CG$5,"<="&DATE(B$26,12,1)) -> 6036027.5 | C30: =SUMIFS($B$12:$CG$12,$B$5:$CG$5,">="&DATE(C$26,1,1),$B$5:$CG$5,"<="&DATE(C$26,12,1)) -> 5788695.1 | D30: =SUMIFS($B$12:$CG$12,$B$5:$CG$5,">="&DATE(D$26,1,1),$B$5:$CG$5,"<="&DATE(D$26,12,1)) -> 6754386.5 | E30: =SUMIFS($B$12:$CG$12,$B$5:$CG$5,">="&DATE(E$26,1,1),$B$5:$CG$5,"<="&DATE(E$26,12,1)) -> 3874844.8 | F30: =SUMIFS($B$12:$CG$12,$B$5:$CG$5,">="&DATE(F$26,1,1),$B$5:$CG$5,"<="&DATE(F$26,12,1)) -> 876711.97 | G30: =SUMIFS($B$12:$CG$12,$B$5:$CG$5,">="&DATE(G$26,1,1),$B$5:$CG$5,"<="&DATE(G$26,12,1)) -> 964680.11 | H30: =SUMIFS($B$12:$CG$12,$B$5:$CG$5,">="&DATE(H$26,1,1),$B$5:$CG$5,"<="&DATE(H$26,12,1)) -> 1061474.8
A31: Payroll Cash Paid | B31: =SUMIFS($B$13:$CG$13,$B$5:$CG$5,">="&DATE(B$26,1,1),$B$5:$CG$5,"<="&DATE(B$26,12,1)) -> 60322073 | C31: =SUMIFS($B$13:$CG$13,$B$5:$CG$5,">="&DATE(C$26,1,1),$B$5:$CG$5,"<="&DATE(C$26,12,1)) -> 71431930 | D31: =SUMIFS($B$13:$CG$13,$B$5:$CG$5,">="&DATE(D$26,1,1),$B$5:$CG$5,"<="&DATE(D$26,12,1)) -> 84152605 | E31: =SUMIFS($B$13:$CG$13,$B$5:$CG$5,">="&DATE(E$26,1,1),$B$5:$CG$5,"<="&DATE(E$26,12,1)) -> 93297269 | F31: =SUMIFS($B$13:$CG$13,$B$5:$CG$5,">="&DATE(F$26,1,1),$B$5:$CG$5,"<="&DATE(F$26,12,1)) -> 1.0409855e+08 | G31: =SUMIFS($B$13:$CG$13,$B$5:$CG$5,">="&DATE(G$26,1,1),$B$5:$CG$5,"<="&DATE(G$26,12,1)) -> 1.1730085e+08 | H31: =SUMIFS($B$13:$CG$13,$B$5:$CG$5,">="&DATE(H$26,1,1),$B$5:$CG$5,"<="&DATE(H$26,12,1)) -> 1.3217753e+08
A32: Net Operating Cash Flow Proxy | B32: =B29-B30-B31 -> -22902996 | C32: =C29-C30-C31 -> -22581387 | D32: =D29-D30-D31 -> -27421169 | E32: =E29-E30-E31 -> -43792348 | F32: =F29-F30-F31 -> -39412962 | G32: =G29-G30-G31 -> -46124796 | H32: =H29-H30-H31 -> -53859767
A34: Cash Bridge
A35: Opening Cash / Net Cash | B35: =_xlfn.XLOOKUP(DATE(B$26,1,1),$B$5:$CG$5,$B$17:$CG$17) -> 10000000 | C35: =_xlfn.XLOOKUP(DATE(C$26,1,1),$B$5:$CG$5,$B$17:$CG$17) -> -12902996 | D35: =_xlfn.XLOOKUP(DATE(D$26,1,1),$B$5:$CG$5,$B$17:$CG$17) -> -35484382 | E35: =_xlfn.XLOOKUP(DATE(E$26,1,1),$B$5:$CG$5,$B$17:$CG$17) -> -62905551 | F35: =_xlfn.XLOOKUP(DATE(F$26,1,1),$B$5:$CG$5,$B$17:$CG$17) -> -1.066979e+08 | G35: =_xlfn.XLOOKUP(DATE(G$26,1,1),$B$5:$CG$5,$B$17:$CG$17) -> -1.4611086e+08 | H35: =_xlfn.XLOOKUP(DATE(H$26,1,1),$B$5:$CG$5,$B$17:$CG$17) -> -1.9223566e+08
A36: Net Operating Cash Flow Proxy | B36: =B32 -> -22902996 | C36: =C32 -> -22581387 | D36: =D32 -> -27421169 | E36: =E32 -> -43792348 | F36: =F32 -> -39412962 | G36: =G32 -> -46124796 | H36: =H32 -> -53859767
A37: Closing Cash / Net Cash | B37: =_xlfn.XLOOKUP(DATE(B$26,12,1),$B$5:$CG$5,$B$19:$CG$19) -> -12902996 | C37: =_xlfn.XLOOKUP(DATE(C$26,12,1),$B$5:$CG$5,$B$19:$CG$19) -> -35484382 | D37: =_xlfn.XLOOKUP(DATE(D$26,12,1),$B$5:$CG$5,$B$19:$CG$19) -> -62905551 | E37: =_xlfn.XLOOKUP(DATE(E$26,12,1),$B$5:$CG$5,$B$19:$CG$19) -> -1.066979e+08 | F37: =_xlfn.XLOOKUP(DATE(F$26,12,1),$B$5:$CG$5,$B$19:$CG$19) -> -1.4611086e+08 | G37: =_xlfn.XLOOKUP(DATE(G$26,12,1),$B$5:$CG$5,$B$19:$CG$19) -> -1.9223566e+08 | H37: =_xlfn.XLOOKUP(DATE(H$26,12,1),$B$5:$CG$5,$B$19:$CG$19) -> -2.4609542e+08
A39: Checks
A40: Cash Movement Check | B40: =B35+B36-B37 -> 0 | C40: =C35+C36-C37 -> 0 | D40: =D35+D36-D37 -> 0 | E40: =E35+E36-E37 -> 0 | F40: =F35+F36-F37 -> 0 | G40: =G35+G36-G37 -> 0 | H40: =H35+H36-H37 -> 0
A41: Cash Continuity Check | B41: 0 | C41: =C35-B37 -> 0 | D41: =D35-C37 -> 0 | E41: =E35-D37 -> 0 | F41: =F35-E37 -> 0 | G41: =G35-F37 -> 0 | H41: =H35-G37 -> 0

Sheet 10_DCF
A1: Nexus Technologies — Discounted Cash Flow | B1: Nexus Technologies — Discounted Cash Flow
A2: ="Scenario: "&'02_Control'!$B$14&" | Currency: "&'02_Control'!$B$12&" | Units: £ actual" -> Scenario: Base | Currency: GBP | Units: £ actual
A5: Period | B5: 2027 | C5: 2028 | D5: 2029
A6: Period Type | B6: =B5&"F" -> 2027F | C6: =C5&"F" -> 2028F | D6: =D5&"F" -> 2029F
A8: Unlevered Free Cash Flow
A9: Recognised Revenue | B9: =_xlfn.XLOOKUP(B$5,'07_Forecast_IS'!$B$28:$H$28,'07_Forecast_IS'!$B$30:$H$30) -> 78829169 | C9: =_xlfn.XLOOKUP(C$5,'07_Forecast_IS'!$B$28:$H$28,'07_Forecast_IS'!$B$30:$H$30) -> 88826681 | D9: =_xlfn.XLOOKUP(D$5,'07_Forecast_IS'!$B$28:$H$28,'07_Forecast_IS'!$B$30:$H$30) -> 1.0009213e+08
A10: Operating Profit | B10: =_xlfn.XLOOKUP(B$5,'07_Forecast_IS'!$B$28:$H$28,'07_Forecast_IS'!$B$34:$H$34) -> -26300805 | C10: =_xlfn.XLOOKUP(C$5,'07_Forecast_IS'!$B$28:$H$28,'07_Forecast_IS'!$B$34:$H$34) -> -29609086 | D10: =_xlfn.XLOOKUP(D$5,'07_Forecast_IS'!$B$28:$H$28,'07_Forecast_IS'!$B$34:$H$34) -> -33334200
A11: Operating Margin | B11: =_xlfn.XLOOKUP(B$5,'07_Forecast_IS'!$B$28:$H$28,'07_Forecast_IS'!$B$35:$H$35) -> -0.33364305 | C11: =_xlfn.XLOOKUP(C$5,'07_Forecast_IS'!$B$28:$H$28,'07_Forecast_IS'!$B$35:$H$35) -> -0.3333355 | D11: =_xlfn.XLOOKUP(D$5,'07_Forecast_IS'!$B$28:$H$28,'07_Forecast_IS'!$B$35:$H$35) -> -0.33303518
A12: Tax Rate | B12: =_xlfn.XLOOKUP("Tax Rate",tbl_assumptions[Driver],tbl_assumptions[Selected Scenario]) -> 0.25 | C12: =_xlfn.XLOOKUP("Tax Rate",tbl_assumptions[Driver],tbl_assumptions[Selected Scenario]) -> 0.25 | D12: =_xlfn.XLOOKUP("Tax Rate",tbl_assumptions[Driver],tbl_assumptions[Selected Scenario]) -> 0.25
A13: Tax on Operating Profit | B13: =-MAX(B10,0)*B12 -> 0 | C13: =-MAX(C10,0)*C12 -> 0 | D13: =-MAX(D10,0)*D12 -> 0
A14: NOPAT | B14: =B10+B13 -> -26300805 | C14: =C10+C13 -> -29609086 | D14: =D10+D13 -> -33334200
A15: Reinvestment % of Revenue | B15: =_xlfn.XLOOKUP("Reinvestment % of Revenue",tbl_assumptions[Driver],tbl_assumptions[Selected Scenario]) -> 0.035 | C15: =_xlfn.XLOOKUP("Reinvestment % of Revenue",tbl_assumptions[Driver],tbl_assumptions[Selected Scenario]) -> 0.035 | D15: =_xlfn.XLOOKUP("Reinvestment % of Revenue",tbl_assumptions[Driver],tbl_assumptions[Selected Scenario]) -> 0.035
A16: Reinvestment | B16: =-B9*B15 -> -2759020.9 | C16: =-C9*C15 -> -3108933.8 | D16: =-D9*D15 -> -3503224.4
A17: Unlevered FCF Proxy | B17: =B14+B16 -> -29059825 | C17: =C14+C16 -> -32718020 | D17: =D14+D16 -> -36837424
A19: Valuation
A20: WACC | B20: =_xlfn.XLOOKUP("WACC",tbl_assumptions[Driver],tbl_assumptions[Selected Scenario]) -> 0.1 | C20: =_xlfn.XLOOKUP("WACC",tbl_assumptions[Driver],tbl_assumptions[Selected Scenario]) -> 0.1 | D20: =_xlfn.XLOOKUP("WACC",tbl_assumptions[Driver],tbl_assumptions[Selected Scenario]) -> 0.1
A21: Terminal Growth Rate | B21: =_xlfn.XLOOKUP("Terminal Growth Rate",tbl_assumptions[Driver],tbl_assumptions[Selected Scenario]) -> 0.025 | C21: =_xlfn.XLOOKUP("Terminal Growth Rate",tbl_assumptions[Driver],tbl_assumptions[Selected Scenario]) -> 0.025 | D21: =_xlfn.XLOOKUP("Terminal Growth Rate",tbl_assumptions[Driver],tbl_assumptions[Selected Scenario]) -> 0.025
A22: Discount Period | B22: =COLUMN(A1)-_xlfn.XLOOKUP("Mid-Year Convention",tbl_assumptions[Driver],tbl_assumptions[Selected Scenario]) -> 0.5 | C22: =COLUMN(B1)-_xlfn.XLOOKUP("Mid-Year Convention",tbl_assumptions[Driver],tbl_assumptions[Selected Scenario]) -> 1.5 | D22: =COLUMN(C1)-_xlfn.XLOOKUP("Mid-Year Convention",tbl_assumptions[Driver],tbl_assumptions[Selected Scenario]) -> 2.5
A23: Discount Factor | B23: =1/(1+B20)^B22 -> 0.95346259 | C23: =1/(1+C20)^C22 -> 0.86678417 | D23: =1/(1+D20)^D22 -> 0.78798561
A24: PV of FCF | B24: =B17*B23 -> -27707456 | C24: =C17*C23 -> -28359462 | D24: =D17*D23 -> -29027360
A25: Terminal Value | B25: ="" | C25: ="" | D25: =IF(D20>D21,D17*(1+D21)/(D20-D21),"Check WACC / g") -> -5.0344479e+08
A26: PV of Terminal Value | B26: ="" | C26: ="" | D26: =D25*D23 -> -3.9670725e+08
A28: Enterprise Value | B28: =SUM(B24:D24)+D26 -> -4.8180153e+08
A30: Checks
A31: Terminal Growth < WACC Check | B31: =IF(_xlfn.XLOOKUP("Terminal Growth Rate",tbl_assumptions[Driver],tbl_assumptions[Selected Scenario])<_xlfn.XLOOKUP("WACC",tbl_assumptions[Driver],tbl_assumptions[Selected Scenario]),"OK","Check") -> OK
A32: FCF Sign Check | B32: =IF(COUNTIF(B17:D17,">0")=0,"All forecast FCF negative","Some positive FCF") -> All forecast FCF negative
A36: Enterprise Value Sensitivity
A38: Terminal Growth \ WACC | B38: 0.08 | C38: 0.09 | D38: 0.1 | E38: 0.11 | F38: 0.12
A39: 0.015 | B39: =IF(B$38>$A39,SUM($B$24:$D$24)+($D$17*(1+$A39)/(B$38-$A39))*$D$23,"n/a") -> -5.3836767e+08 | C39: =IF(C$38>$A39,SUM($B$24:$D$24)+($D$17*(1+$A39)/(C$38-$A39))*$D$23,"n/a") -> -4.7793122e+08 | D39: =IF(D$38>$A39,SUM($B$24:$D$24)+($D$17*(1+$A39)/(D$38-$A39))*$D$23,"n/a") -> -4.3171511e+08 | E39: =IF(E$38>$A39,SUM($B$24:$D$24)+($D$17*(1+$A39)/(E$38-$A39))*$D$23,"n/a") -> -3.952287e+08 | F39: =IF(F$38>$A39,SUM($B$24:$D$24)+($D$17*(1+$A39)/(F$38-$A39))*$D$23,"n/a") -> -3.6569209e+08
A40: 0.02 | B40: =IF(B$38>$A40,SUM($B$24:$D$24)+($D$17*(1+$A40)/(B$38-$A40))*$D$23,"n/a") -> -5.785594e+08 | C40: =IF(C$38>$A40,SUM($B$24:$D$24)+($D$17*(1+$A40)/(C$38-$A40))*$D$23,"n/a") -> -5.0806438e+08 | D40: =IF(D$38>$A40,SUM($B$24:$D$24)+($D$17*(1+$A40)/(D$38-$A40))*$D$23,"n/a") -> -4.5519312e+08 | E40: =IF(E$38>$A40,SUM($B$24:$D$24)+($D$17*(1+$A40)/(E$38-$A40))*$D$23,"n/a") -> -4.1407103e+08 | F40: =IF(F$38>$A40,SUM($B$24:$D$24)+($D$17*(1+$A40)/(F$38-$A40))*$D$23,"n/a") -> -3.8117335e+08
A41: 0.025 | B41: =IF(B$38>$A41,SUM($B$24:$D$24)+($D$17*(1+$A41)/(B$38-$A41))*$D$23,"n/a") -> -6.2605872e+08 | C41: =IF(C$38>$A41,SUM($B$24:$D$24)+($D$17*(1+$A41)/(C$38-$A41))*$D$23,"n/a") -> -5.4283342e+08 | D41: =IF(D$38>$A41,SUM($B$24:$D$24)+($D$17*(1+$A41)/(D$38-$A41))*$D$23,"n/a") -> -4.8180153e+08 | E41: =IF(E$38>$A41,SUM($B$24:$D$24)+($D$17*(1+$A41)/(E$38-$A41))*$D$23,"n/a") -> -4.3513009e+08 | F41: =IF(F$38>$A41,SUM($B$24:$D$24)+($D$17*(1+$A41)/(F$38-$A41))*$D$23,"n/a") -> -3.9828422e+08
A42: 0.03 | B42: =IF(B$38>$A42,SUM($B$24:$D$24)+($D$17*(1+$A42)/(B$38-$A42))*$D$23,"n/a") -> -6.830579e+08 | C42: =IF(C$38>$A42,SUM($B$24:$D$24)+($D$17*(1+$A42)/(C$38-$A42))*$D$23,"n/a") -> -5.8339729e+08 | D42: =IF(D$38>$A42,SUM($B$24:$D$24)+($D$17*(1+$A42)/(D$38-$A42))*$D$23,"n/a") -> -5.1221115e+08 | E42: =IF(E$38>$A42,SUM($B$24:$D$24)+($D$17*(1+$A42)/(E$38-$A42))*$D$23,"n/a") -> -4.5882154e+08 | F42: =IF(F$38>$A42,SUM($B$24:$D$24)+($D$17*(1+$A42)/(F$38-$A42))*$D$23,"n/a") -> -4.1729629e+08
A43: 0.035 | B43: =IF(B$38>$A43,SUM($B$24:$D$24)+($D$17*(1+$A43)/(B$38-$A43))*$D$23,"n/a") -> -7.5272356e+08 | C43: =IF(C$38>$A43,SUM($B$24:$D$24)+($D$17*(1+$A43)/(C$38-$A43))*$D$23,"n/a") -> -6.3133642e+08 | D43: =IF(D$38>$A43,SUM($B$24:$D$24)+($D$17*(1+$A43)/(D$38-$A43))*$D$23,"n/a") -> -5.4729917e+08 | E43: =IF(E$38>$A43,SUM($B$24:$D$24)+($D$17*(1+$A43)/(E$38-$A43))*$D$23,"n/a") -> -4.8567185e+08 | F43: =IF(F$38>$A43,SUM($B$24:$D$24)+($D$17*(1+$A43)/(F$38-$A43))*$D$23,"n/a") -> -4.3854507e+08
A46: WACC greater than terminal growth check | B46: =IF(MIN(B38:F38)>MAX(A39:A43),"OK","Check: terminal growth >= WACC in sensitivity range") -> OK
A47: Main EV ties to sensitivity midpoint | B47: =D41-$B$28 -> 0

Sheet 11_Audit_Checks
A1: Nexus Technologies — Model Audit Checks
A2: ARR modelling decision: Headline ARR uses active_arr_gbp, renamed headline_arr_gbp. ending_arr_gbp is treated as ARR monthly run-rate source and is not used as the headline ARR balance. ARR bridge components are not used to forecast ARR until bridge reconciliation is resolved.
A4: Feed Integrity
A5: Expected | B5: 42
A6: Actual | B6: =ROWS(tbl_model_feed_final[reporting_month_date]) -> 42
A7: Status | B7: =IF(B5=B6,"OK","Check") -> OK
A8: First Actual Month | B8: =MIN(tbl_model_feed_final[reporting_month_date]) -> 44927
A9: Last Actual Month | B9: =MAX(tbl_model_feed_final[reporting_month_date]) -> 46174
A10: Duplicate Month Count | B10: =ROWS(tbl_model_feed_final[reporting_month_date])-ROWS(_xlfn.UNIQUE(tbl_model_feed_final[reporting_month_date])) -> 0
A11: Monthly Span Check | B11: =DATEDIF(MIN(tbl_model_feed_final[reporting_month_date]),MAX(tbl_model_feed_final[reporting_month_date]),"m")+1 -> 42
A12: Month Span Status | B12: =IF(B11=B6,"OK","Check") -> OK
A14: Financial Logic Checks
A15: Operating profit check | B15: {=MAX(ABS(_xlfn._xlws.FILTER('05_Monthly_Model'!B24:CG24,'05_Monthly_Model'!B$5:CG$5="Actual")))} -> 0
A16: Operating profit check Status | B16: =IF(B15<=1,"OK","Check") -> OK
A17: Operating expense proxy check | B17: {=MAX(ABS(_xlfn._xlws.FILTER('05_Monthly_Model'!B22:CG22,'05_Monthly_Model'!B$5:CG$5="Actual")))} -> 0
A18: Operating expense proxy check Status | B18: =IF(B17<=1,"OK","Check") -> OK
A19: Deferred revenue rollforward check | B19: =COUNTIF(tbl_model_feed_final[deferred_revenue_model_status],"<>OK") -> 1
A20: Control Exception Present | B20: =IF(B19=0,"OK","Control Exception Present") -> Control Exception Present
A24: Source Definition Checks
A25: ARR monthly run-rate variance | B25: {=MAX(ABS(tbl_model_feed_final[arr_monthly_run_rate_variance_gbp]))} -> 6980.6367
A26: ARR monthly run-rate variance status | B26: =IF(B25<=1,"OK","Rounding / Definition Difference") -> Rounding / Definition Difference
A27: ARR bridge variance | B27: {=MAX(ABS(tbl_model_feed_final[arr_bridge_variance_gbp]))} -> 96867.64
A28: ARR bridge variance status | B28: =IF(B27<=1,"OK","Source Definition Difference") -> Source Definition Difference
A29: ARR bridge usable for forecast? | B29: =IF(COUNTIF(tbl_model_feed_final[arr_bridge_status],"OK")=ROWS(tbl_model_feed_final[arr_bridge_status]),"Yes","No - forecast headline ARR directly") -> No - forecast headline ARR directly
A30: Revenue waterfall vs O2C billings | B30: =COUNTIF(tbl_model_feed_final[revenue_vs_o2c_billings_status],"Definition Difference") -> 33
A31: Revenue waterfall vs O2C billings Status | B31: =IF(B30=0,"OK","Definition Difference Present") -> Definition Difference Present
A34: Control Exception Summary
A35: AP control exceptions | B35: =COUNTIF(tbl_model_feed_final[ap_control_status],"Control Exception") -> 3
A36: AP control exceptions Status | B36: =IF(B35=0,"OK","Control Exception Present") -> Control Exception Present
A37: Workforce control exceptions | B37: =COUNTIF(tbl_model_feed_final[workforce_control_status],"Control Exception") -> 42
A38: Workforce control exceptions Status | B38: =IF(B37=0,"OK","Control Exception Present") -> Control Exception Present
A39: SaaS ARR control exceptions | B39: =COUNTIF(tbl_model_feed_final[saas_arr_control_status],"Control Exception") -> 42
A40: SaaS ARR control exceptions Status | B40: =IF(B39=0,"OK","Control Exception Present") -> Control Exception Present
A41: SaaS retention exceptions | B41: =COUNTIF(tbl_model_feed_final[saas_retention_control_status],"Control Exception") -> 42
A42: SaaS retention exceptions Status | B42: =IF(B41=0,"OK","Control Exception Present") -> Control Exception Present
A43: Deferred revenue checks | B43: =COUNTIF(tbl_model_feed_final[deferred_revenue_model_status],"Check") -> 1
A46: Model-readiness checks
A47: Forecast period populated check | B47: =COUNTA('05_Monthly_Model'!AR10:CG34) -> 882
A48: Forecast period populated check status | B48: =IF(B47>0,"OK","Check - forecast period blank") -> OK
A49: Unit scale factor check | B49: ='02_Control'!$B$18 -> 1
A50: Unit scale factor check Status | B50: =IF(OR(B49=1,B49=1000,B49=1000000),"OK","Check") -> OK
A51: Scenario selection valid check | B51: =IF(OR('02_Control'!$B$14="Base",'02_Control'!$B$14="Upside",'02_Control'!$B$14="Downside"),"OK","Check") -> OK

Sheet 12_Outputs
